Workbook

Sheet Synthese
A1: Suivi des modifications Jira RSS
A4: Exports analysés | B4: 2 | D4: Cette synthèse est volontairement statique pour garantir l'ouverture Excel. La vue interactive demandée est en onglet 2 : Slide_2_Story_AC. Elle permet de choisir le sprint et le statut pour suivre les modifications Story sur Description et Acceptance Criteria.
A5: Premier export | B5: 46178.648
A6: Dernier export | B6: 46181.338
A7: Période début
A8: Période fin
A9: Périmètre | B9: Aucun filtre en ligne de commande
A12: Tickets modifiés | D12: Total modifications | G12: Descriptions modifiées | J12: AC modifiés
A13: 1 | D13: 4 | G13: 0 | J13: 0
A16: Changements statut | D16: Changements sprint | G16: Tickets apparus | J16: Tickets disparus
A17: 1 | D17: 0 | G17: 0 | J17: 0
A24: Modifications par champ
A25: Champ modifié | B25: Modifications | C25: Tickets concernés
A26: Assigné | B26: 1 | C26: 1
A27: Commentaires | B27: 1 | C27: 1
A28: Custom fields | B28: 1 | C28: 1
A29: Statut | B29: 1 | C29: 1
A40: Onglet 2 à utiliser : Slide_2_Story_AC — suivi visuel des modifications Story sur Description et Acceptance Criteria.

Sheet Slide_2_Story_AC
A1: Slide 2 - Évolution des Stories : Description & Acceptance Criteria
A4: Objectif Suivre, par sprint, les changements intervenus sur les tickets de type Story pour les champs Description et Acceptance Criteria. | D4: Sprint à analyser | E4: Sprint 17 2026 | H4: Statut | I4: Tous
D6: Sélectionne un sprint en E4 et, si besoin, un statut en I4. La page utilise uniquement des formules Excel compatibles : INDEX/MATCH et SUMIFS. Type de ticket fixé : Story. Champs suivis : Description et Acceptance Criteria.
A10: Stories dans le dernier export | D10: Stories impactées | G10: Total modifs Desc/AC | J10: Descriptions modifiées
A11: =IFERROR(INDEX(_Story_AC_KPI!$D:$D,MATCH($E$4&"|"&$I$4,_Story_AC_KPI!$A:$A,0)),0) -> 20 | D11: =IFERROR(INDEX(_Story_AC_KPI!$E:$E,MATCH($E$4&"|"&$I$4,_Story_AC_KPI!$A:$A,0)),0) -> 0 | G11: =IFERROR(INDEX(_Story_AC_KPI!$F:$F,MATCH($E$4&"|"&$I$4,_Story_AC_KPI!$A:$A,0)),0) -> 0 | J11: =IFERROR(INDEX(_Story_AC_KPI!$G:$G,MATCH($E$4&"|"&$I$4,_Story_AC_KPI!$A:$A,0)),0) -> 0
A14: AC modifiés | D14: Stories avec Desc + AC | G14: Taux de stories impactées | J14: Dernière détection
A15: =IFERROR(INDEX(_Story_AC_KPI!$H:$H,MATCH($E$4&"|"&$I$4,_Story_AC_KPI!$A:$A,0)),0) -> 0 | D15: =IFERROR(INDEX(_Story_AC_KPI!$K:$K,MATCH($E$4&"|"&$I$4,_Story_AC_KPI!$A:$A,0)),0) -> 0 | G15: =IFERROR(INDEX(_Story_AC_KPI!$L:$L,MATCH($E$4&"|"&$I$4,_Story_AC_KPI!$A:$A,0)),0) -> 0 | J15: =IFERROR(INDEX(_Story_AC_KPI!$N:$N,MATCH($E$4&"|"&$I$4,_Story_AC_KPI!$A:$A,0)),"") -> 0
A20: Répartition des changements Story
A21: Champ | B21: Modifications | C21: Tickets concernés
A22: Description | B22: =IFERROR(INDEX(_Story_AC_Field!$E:$E,MATCH($E$4&"|"&$I$4&"|"&A22,_Story_AC_Field!$A:$A,0)),0) -> 0 | C22: =IFERROR(INDEX(_Story_AC_Field!$F:$F,MATCH($E$4&"|"&$I$4&"|"&A22,_Story_AC_Field!$A:$A,0)),0) -> 0
A23: Acceptance Criteria | B23: =IFERROR(INDEX(_Story_AC_Field!$E:$E,MATCH($E$4&"|"&$I$4&"|"&A23,_Story_AC_Field!$A:$A,0)),0) -> 0 | C23: =IFERROR(INDEX(_Story_AC_Field!$F:$F,MATCH($E$4&"|"&$I$4&"|"&A23,_Story_AC_Field!$A:$A,0)),0) -> 0
A34: Évolution par fenêtre d'export
A35: Date de détection | B35: Descriptions | C35: AC | D35: Tickets impactés
A36: 2026-06-08 08:07:02 UTC | B36: =IFERROR(INDEX(_Story_AC_Evo!$E:$E,MATCH($E$4&"|"&$I$4&"|"&A36,_Story_AC_Evo!$A:$A,0)),0) -> 0 | C36: =IFERROR(INDEX(_Story_AC_Evo!$F:$F,MATCH($E$4&"|"&$I$4&"|"&A36,_Story_AC_Evo!$A:$A,0)),0) -> 0 | D36: =IFERROR(INDEX(_Story_AC_Evo!$G:$G,MATCH($E$4&"|"&$I$4&"|"&A36,_Story_AC_Evo!$A:$A,0)),0) -> 0
A68: Top tickets Story modifiés sur Description / AC
A69: Rang | B69: Key | C69: Statut | D69: Desc | E69: AC | F69: Total | G69: Dernière détection | H69: Résumé | I69: Lien
A70: 1 | B70: =IFERROR(INDEX(_Story_AC_Top!$F:$F,MATCH($E$4&"|"&$I$4&"|"&A70,_Story_AC_Top!$A:$A,0)),"") | C70: =IFERROR(INDEX(_Story_AC_Top!$H:$H,MATCH($E$4&"|"&$I$4&"|"&A70,_Story_AC_Top!$A:$A,0)),"") | D70: =IFERROR(INDEX(_Story_AC_Top!$I:$I,MATCH($E$4&"|"&$I$4&"|"&A70,_Story_AC_Top!$A:$A,0)),0) -> 0 | E70: =IFERROR(INDEX(_Story_AC_Top!$J:$J,MATCH($E$4&"|"&$I$4&"|"&A70,_Story_AC_Top!$A:$A,0)),0) -> 0 | F70: =IFERROR(INDEX(_Story_AC_Top!$K:$K,MATCH($E$4&"|"&$I$4&"|"&A70,_Story_AC_Top!$A:$A,0)),0) -> 0 | G70: =IFERROR(INDEX(_Story_AC_Top!$L:$L,MATCH($E$4&"|"&$I$4&"|"&A70,_Story_AC_Top!$A:$A,0)),"") | H70: =IFERROR(INDEX(_Story_AC_Top!$G:$G,MATCH($E$4&"|"&$I$4&"|"&A70,_Story_AC_Top!$A:$A,0)),"") | I70: =IFERROR(INDEX(_Story_AC_Top!$M:$M,MATCH($E$4&"|"&$I$4&"|"&A70,_Story_AC_Top!$A:$A,0)),"")
A71: 2 | B71: =IFERROR(INDEX(_Story_AC_Top!$F:$F,MATCH($E$4&"|"&$I$4&"|"&A71,_Story_AC_Top!$A:$A,0)),"") | C71: =IFERROR(INDEX(_Story_AC_Top!$H:$H,MATCH($E$4&"|"&$I$4&"|"&A71,_Story_AC_Top!$A:$A,0)),"") | D71: =IFERROR(INDEX(_Story_AC_Top!$I:$I,MATCH($E$4&"|"&$I$4&"|"&A71,_Story_AC_Top!$A:$A,0)),0) -> 0 | E71: =IFERROR(INDEX(_Story_AC_Top!$J:$J,MATCH($E$4&"|"&$I$4&"|"&A71,_Story_AC_Top!$A:$A,0)),0) -> 0 | F71: =IFERROR(INDEX(_Story_AC_Top!$K:$K,MATCH($E$4&"|"&$I$4&"|"&A71,_Story_AC_Top!$A:$A,0)),0) -> 0 | G71: =IFERROR(INDEX(_Story_AC_Top!$L:$L,MATCH($E$4&"|"&$I$4&"|"&A71,_Story_AC_Top!$A:$A,0)),"") | H71: =IFERROR(INDEX(_Story_AC_Top!$G:$G,MATCH($E$4&"|"&$I$4&"|"&A71,_Story_AC_Top!$A:$A,0)),"") | I71: =IFERROR(INDEX(_Story_AC_Top!$M:$M,MATCH($E$4&"|"&$I$4&"|"&A71,_Story_AC_Top!$A:$A,0)),"")
A72: 3 | B72: =IFERROR(INDEX(_Story_AC_Top!$F:$F,MATCH($E$4&"|"&$I$4&"|"&A72,_Story_AC_Top!$A:$A,0)),"") | C72: =IFERROR(INDEX(_Story_AC_Top!$H:$H,MATCH($E$4&"|"&$I$4&"|"&A72,_Story_AC_Top!$A:$A,0)),"") | D72: =IFERROR(INDEX(_Story_AC_Top!$I:$I,MATCH($E$4&"|"&$I$4&"|"&A72,_Story_AC_Top!$A:$A,0)),0) -> 0 | E72: =IFERROR(INDEX(_Story_AC_Top!$J:$J,MATCH($E$4&"|"&$I$4&"|"&A72,_Story_AC_Top!$A:$A,0)),0) -> 0 | F72: =IFERROR(INDEX(_Story_AC_Top!$K:$K,MATCH($E$4&"|"&$I$4&"|"&A72,_Story_AC_Top!$A:$A,0)),0) -> 0 | G72: =IFERROR(INDEX(_Story_AC_Top!$L:$L,MATCH($E$4&"|"&$I$4&"|"&A72,_Story_AC_Top!$A:$A,0)),"") | H72: =IFERROR(INDEX(_Story_AC_Top!$G:$G,MATCH($E$4&"|"&$I$4&"|"&A72,_Story_AC_Top!$A:$A,0)),"") | I72: =IFERROR(INDEX(_Story_AC_Top!$M:$M,MATCH($E$4&"|"&$I$4&"|"&A72,_Story_AC_Top!$A:$A,0)),"")
A73: 4 | B73: =IFERROR(INDEX(_Story_AC_Top!$F:$F,MATCH($E$4&"|"&$I$4&"|"&A73,_Story_AC_Top!$A:$A,0)),"") | C73: =IFERROR(INDEX(_Story_AC_Top!$H:$H,MATCH($E$4&"|"&$I$4&"|"&A73,_Story_AC_Top!$A:$A,0)),"") | D73: =IFERROR(INDEX(_Story_AC_Top!$I:$I,MATCH($E$4&"|"&$I$4&"|"&A73,_Story_AC_Top!$A:$A,0)),0) -> 0 | E73: =IFERROR(INDEX(_Story_AC_Top!$J:$J,MATCH($E$4&"|"&$I$4&"|"&A73,_Story_AC_Top!$A:$A,0)),0) -> 0 | F73: =IFERROR(INDEX(_Story_AC_Top!$K:$K,MATCH($E$4&"|"&$I$4&"|"&A73,_Story_AC_Top!$A:$A,0)),0) -> 0 | G73: =IFERROR(INDEX(_Story_AC_Top!$L:$L,MATCH($E$4&"|"&$I$4&"|"&A73,_Story_AC_Top!$A:$A,0)),"") | H73: =IFERROR(INDEX(_Story_AC_Top!$G:$G,MATCH($E$4&"|"&$I$4&"|"&A73,_Story_AC_Top!$A:$A,0)),"") | I73: =IFERROR(INDEX(_Story_AC_Top!$M:$M,MATCH($E$4&"|"&$I$4&"|"&A73,_Story_AC_Top!$A:$A,0)),"")
A74: 5 | B74: =IFERROR(INDEX(_Story_AC_Top!$F:$F,MATCH($E$4&"|"&$I$4&"|"&A74,_Story_AC_Top!$A:$A,0)),"") | C74: =IFERROR(INDEX(_Story_AC_Top!$H:$H,MATCH($E$4&"|"&$I$4&"|"&A74,_Story_AC_Top!$A:$A,0)),"") | D74: =IFERROR(INDEX(_Story_AC_Top!$I:$I,MATCH($E$4&"|"&$I$4&"|"&A74,_Story_AC_Top!$A:$A,0)),0) -> 0 | E74: =IFERROR(INDEX(_Story_AC_Top!$J:$J,MATCH($E$4&"|"&$I$4&"|"&A74,_Story_AC_Top!$A:$A,0)),0) -> 0 | F74: =IFERROR(INDEX(_Story_AC_Top!$K:$K,MATCH($E$4&"|"&$I$4&"|"&A74,_Story_AC_Top!$A:$A,0)),0) -> 0 | G74: =IFERROR(INDEX(_Story_AC_Top!$L:$L,MATCH($E$4&"|"&$I$4&"|"&A74,_Story_AC_Top!$A:$A,0)),"") | H74: =IFERROR(INDEX(_Story_AC_Top!$G:$G,MATCH($E$4&"|"&$I$4&"|"&A74,_Story_AC_Top!$A:$A,0)),"") | I74: =IFERROR(INDEX(_Story_AC_Top!$M:$M,MATCH($E$4&"|"&$I$4&"|"&A74,_Story_AC_Top!$A:$A,0)),"")
A75: 6 | B75: =IFERROR(INDEX(_Story_AC_Top!$F:$F,MATCH($E$4&"|"&$I$4&"|"&A75,_Story_AC_Top!$A:$A,0)),"") | C75: =IFERROR(INDEX(_Story_AC_Top!$H:$H,MATCH($E$4&"|"&$I$4&"|"&A75,_Story_AC_Top!$A:$A,0)),"") | D75: =IFERROR(INDEX(_Story_AC_Top!$I:$I,MATCH($E$4&"|"&$I$4&"|"&A75,_Story_AC_Top!$A:$A,0)),0) -> 0 | E75: =IFERROR(INDEX(_Story_AC_Top!$J:$J,MATCH($E$4&"|"&$I$4&"|"&A75,_Story_AC_Top!$A:$A,0)),0) -> 0 | F75: =IFERROR(INDEX(_Story_AC_Top!$K:$K,MATCH($E$4&"|"&$I$4&"|"&A75,_Story_AC_Top!$A:$A,0)),0) -> 0 | G75: =IFERROR(INDEX(_Story_AC_Top!$L:$L,MATCH($E$4&"|"&$I$4&"|"&A75,_Story_AC_Top!$A:$A,0)),"") | H75: =IFERROR(INDEX(_Story_AC_Top!$G:$G,MATCH($E$4&"|"&$I$4&"|"&A75,_Story_AC_Top!$A:$A,0)),"") | I75: =IFERROR(INDEX(_Story_AC_Top!$M:$M,MATCH($E$4&"|"&$I$4&"|"&A75,_Story_AC_Top!$A:$A,0)),"")
A76: 7 | B76: =IFERROR(INDEX(_Story_AC_Top!$F:$F,MATCH($E$4&"|"&$I$4&"|"&A76,_Story_AC_Top!$A:$A,0)),"") | C76: =IFERROR(INDEX(_Story_AC_Top!$H:$H,MATCH($E$4&"|"&$I$4&"|"&A76,_Story_AC_Top!$A:$A,0)),"") | D76: =IFERROR(INDEX(_Story_AC_Top!$I:$I,MATCH($E$4&"|"&$I$4&"|"&A76,_Story_AC_Top!$A:$A,0)),0) -> 0 | E76: =IFERROR(INDEX(_Story_AC_Top!$J:$J,MATCH($E$4&"|"&$I$4&"|"&A76,_Story_AC_Top!$A:$A,0)),0) -> 0 | F76: =IFERROR(INDEX(_Story_AC_Top!$K:$K,MATCH($E$4&"|"&$I$4&"|"&A76,_Story_AC_Top!$A:$A,0)),0) -> 0 | G76: =IFERROR(INDEX(_Story_AC_Top!$L:$L,MATCH($E$4&"|"&$I$4&"|"&A76,_Story_AC_Top!$A:$A,0)),"") | H76: =IFERROR(INDEX(_Story_AC_Top!$G:$G,MATCH($E$4&"|"&$I$4&"|"&A76,_Story_AC_Top!$A:$A,0)),"") | I76: =IFERROR(INDEX(_Story_AC_Top!$M:$M,MATCH($E$4&"|"&$I$4&"|"&A76,_Story_AC_Top!$A:$A,0)),"")
A77: 8 | B77: =IFERROR(INDEX(_Story_AC_Top!$F:$F,MATCH($E$4&"|"&$I$4&"|"&A77,_Story_AC_Top!$A:$A,0)),"") | C77: =IFERROR(INDEX(_Story_AC_Top!$H:$H,MATCH($E$4&"|"&$I$4&"|"&A77,_Story_AC_Top!$A:$A,0)),"") | D77: =IFERROR(INDEX(_Story_AC_Top!$I:$I,MATCH($E$4&"|"&$I$4&"|"&A77,_Story_AC_Top!$A:$A,0)),0) -> 0 | E77: =IFERROR(INDEX(_Story_AC_Top!$J:$J,MATCH($E$4&"|"&$I$4&"|"&A77,_Story_AC_Top!$A:$A,0)),0) -> 0 | F77: =IFERROR(INDEX(_Story_AC_Top!$K:$K,MATCH($E$4&"|"&$I$4&"|"&A77,_Story_AC_Top!$A:$A,0)),0) -> 0 | G77: =IFERROR(INDEX(_Story_AC_Top!$L:$L,MATCH($E$4&"|"&$I$4&"|"&A77,_Story_AC_Top!$A:$A,0)),"") | H77: =IFERROR(INDEX(_Story_AC_Top!$G:$G,MATCH($E$4&"|"&$I$4&"|"&A77,_Story_AC_Top!$A:$A,0)),"") | I77: =IFERROR(INDEX(_Story_AC_Top!$M:$M,MATCH($E$4&"|"&$I$4&"|"&A77,_Story_AC_Top!$A:$A,0)),"")
A78: 9 | B78: =IFERROR(INDEX(_Story_AC_Top!$F:$F,MATCH($E$4&"|"&$I$4&"|"&A78,_Story_AC_Top!$A:$A,0)),"") | C78: =IFERROR(INDEX(_Story_AC_Top!$H:$H,MATCH($E$4&"|"&$I$4&"|"&A78,_Story_AC_Top!$A:$A,0)),"") | D78: =IFERROR(INDEX(_Story_AC_Top!$I:$I,MATCH($E$4&"|"&$I$4&"|"&A78,_Story_AC_Top!$A:$A,0)),0) -> 0 | E78: =IFERROR(INDEX(_Story_AC_Top!$J:$J,MATCH($E$4&"|"&$I$4&"|"&A78,_Story_AC_Top!$A:$A,0)),0) -> 0 | F78: =IFERROR(INDEX(_Story_AC_Top!$K:$K,MATCH($E$4&"|"&$I$4&"|"&A78,_Story_AC_Top!$A:$A,0)),0) -> 0 | G78: =IFERROR(INDEX(_Story_AC_Top!$L:$L,MATCH($E$4&"|"&$I$4&"|"&A78,_Story_AC_Top!$A:$A,0)),"") | H78: =IFERROR(INDEX(_Story_AC_Top!$G:$G,MATCH($E$4&"|"&$I$4&"|"&A78,_Story_AC_Top!$A:$A,0)),"") | I78: =IFERROR(INDEX(_Story_AC_Top!$M:$M,MATCH($E$4&"|"&$I$4&"|"&A78,_Story_AC_Top!$A:$A,0)),"")
A79: 10 | B79: =IFERROR(INDEX(_Story_AC_Top!$F:$F,MATCH($E$4&"|"&$I$4&"|"&A79,_Story_AC_Top!$A:$A,0)),"") | C79: =IFERROR(INDEX(_Story_AC_Top!$H:$H,MATCH($E$4&"|"&$I$4&"|"&A79,_Story_AC_Top!$A:$A,0)),"") | D79: =IFERROR(INDEX(_Story_AC_Top!$I:$I,MATCH($E$4&"|"&$I$4&"|"&A79,_Story_AC_Top!$A:$A,0)),0) -> 0 | E79: =IFERROR(INDEX(_Story_AC_Top!$J:$J,MATCH($E$4&"|"&$I$4&"|"&A79,_Story_AC_Top!$A:$A,0)),0) -> 0 | F79: =IFERROR(INDEX(_Story_AC_Top!$K:$K,MATCH($E$4&"|"&$I$4&"|"&A79,_Story_AC_Top!$A:$A,0)),0) -> 0 | G79: =IFERROR(INDEX(_Story_AC_Top!$L:$L,MATCH($E$4&"|"&$I$4&"|"&A79,_Story_AC_Top!$A:$A,0)),"") | H79: =IFERROR(INDEX(_Story_AC_Top!$G:$G,MATCH($E$4&"|"&$I$4&"|"&A79,_Story_AC_Top!$A:$A,0)),"") | I79: =IFERROR(INDEX(_Story_AC_Top!$M:$M,MATCH($E$4&"|"&$I$4&"|"&A79,_Story_AC_Top!$A:$A,0)),"")
A83: Derniers changements détectés - extraits avant / après
A84: Rang | B84: Détection | C84: Key | D84: Champ | E84: Statut | F84: Extrait avant | G84: Extrait après | H84: Lien
A85: 1 | B85: =IFERROR(INDEX(_Story_AC_Recent!$E:$E,MATCH($E$4&"|"&$I$4&"|"&A85,_Story_AC_Recent!$A:$A,0)),"") | C85: =IFERROR(INDEX(_Story_AC_Recent!$F:$F,MATCH($E$4&"|"&$I$4&"|"&A85,_Story_AC_Recent!$A:$A,0)),"") | D85: =IFERROR(INDEX(_Story_AC_Recent!$G:$G,MATCH($E$4&"|"&$I$4&"|"&A85,_Story_AC_Recent!$A:$A,0)),"") | E85: =IFERROR(INDEX(_Story_AC_Recent!$H:$H,MATCH($E$4&"|"&$I$4&"|"&A85,_Story_AC_Recent!$A:$A,0)),"") | F85: =IFERROR(INDEX(_Story_AC_Recent!$J:$J,MATCH($E$4&"|"&$I$4&"|"&A85,_Story_AC_Recent!$A:$A,0)),"") | G85: =IFERROR(INDEX(_Story_AC_Recent!$K:$K,MATCH($E$4&"|"&$I$4&"|"&A85,_Story_AC_Recent!$A:$A,0)),"") | H85: =IFERROR(INDEX(_Story_AC_Recent!$L:$L,MATCH($E$4&"|"&$I$4&"|"&A85,_Story_AC_Recent!$A:$A,0)),"")
A86: 2 | B86: =IFERROR(INDEX(_Story_AC_Recent!$E:$E,MATCH($E$4&"|"&$I$4&"|"&A86,_Story_AC_Recent!$A:$A,0)),"") | C86: =IFERROR(INDEX(_Story_AC_Recent!$F:$F,MATCH($E$4&"|"&$I$4&"|"&A86,_Story_AC_Recent!$A:$A,0)),"") | D86: =IFERROR(INDEX(_Story_AC_Recent!$G:$G,MATCH($E$4&"|"&$I$4&"|"&A86,_Story_AC_Recent!$A:$A,0)),"") | E86: =IFERROR(INDEX(_Story_AC_Recent!$H:$H,MATCH($E$4&"|"&$I$4&"|"&A86,_Story_AC_Recent!$A:$A,0)),"") | F86: =IFERROR(INDEX(_Story_AC_Recent!$J:$J,MATCH($E$4&"|"&$I$4&"|"&A86,_Story_AC_Recent!$A:$A,0)),"") | G86: =IFERROR(INDEX(_Story_AC_Recent!$K:$K,MATCH($E$4&"|"&$I$4&"|"&A86,_Story_AC_Recent!$A:$A,0)),"") | H86: =IFERROR(INDEX(_Story_AC_Recent!$L:$L,MATCH($E$4&"|"&$I$4&"|"&A86,_Story_AC_Recent!$A:$A,0)),"")
A87: 3 | B87: =IFERROR(INDEX(_Story_AC_Recent!$E:$E,MATCH($E$4&"|"&$I$4&"|"&A87,_Story_AC_Recent!$A:$A,0)),"") | C87: =IFERROR(INDEX(_Story_AC_Recent!$F:$F,MATCH($E$4&"|"&$I$4&"|"&A87,_Story_AC_Recent!$A:$A,0)),"") | D87: =IFERROR(INDEX(_Story_AC_Recent!$G:$G,MATCH($E$4&"|"&$I$4&"|"&A87,_Story_AC_Recent!$A:$A,0)),"") | E87: =IFERROR(INDEX(_Story_AC_Recent!$H:$H,MATCH($E$4&"|"&$I$4&"|"&A87,_Story_AC_Recent!$A:$A,0)),"") | F87: =IFERROR(INDEX(_Story_AC_Recent!$J:$J,MATCH($E$4&"|"&$I$4&"|"&A87,_Story_AC_Recent!$A:$A,0)),"") | G87: =IFERROR(INDEX(_Story_AC_Recent!$K:$K,MATCH($E$4&"|"&$I$4&"|"&A87,_Story_AC_Recent!$A:$A,0)),"") | H87: =IFERROR(INDEX(_Story_AC_Recent!$L:$L,MATCH($E$4&"|"&$I$4&"|"&A87,_Story_AC_Recent!$A:$A,0)),"")
A88: 4 | B88: =IFERROR(INDEX(_Story_AC_Recent!$E:$E,MATCH($E$4&"|"&$I$4&"|"&A88,_Story_AC_Recent!$A:$A,0)),"") | C88: =IFERROR(INDEX(_Story_AC_Recent!$F:$F,MATCH($E$4&"|"&$I$4&"|"&A88,_Story_AC_Recent!$A:$A,0)),"") | D88: =IFERROR(INDEX(_Story_AC_Recent!$G:$G,MATCH($E$4&"|"&$I$4&"|"&A88,_Story_AC_Recent!$A:$A,0)),"") | E88: =IFERROR(INDEX(_Story_AC_Recent!$H:$H,MATCH($E$4&"|"&$I$4&"|"&A88,_Story_AC_Recent!$A:$A,0)),"") | F88: =IFERROR(INDEX(_Story_AC_Recent!$J:$J,MATCH($E$4&"|"&$I$4&"|"&A88,_Story_AC_Recent!$A:$A,0)),"") | G88: =IFERROR(INDEX(_Story_AC_Recent!$K:$K,MATCH($E$4&"|"&$I$4&"|"&A88,_Story_AC_Recent!$A:$A,0)),"") | H88: =IFERROR(INDEX(_Story_AC_Recent!$L:$L,MATCH($E$4&"|"&$I$4&"|"&A88,_Story_AC_Recent!$A:$A,0)),"")
A89: 5 | B89: =IFERROR(INDEX(_Story_AC_Recent!$E:$E,MATCH($E$4&"|"&$I$4&"|"&A89,_Story_AC_Recent!$A:$A,0)),"") | C89: =IFERROR(INDEX(_Story_AC_Recent!$F:$F,MATCH($E$4&"|"&$I$4&"|"&A89,_Story_AC_Recent!$A:$A,0)),"") | D89: =IFERROR(INDEX(_Story_AC_Recent!$G:$G,MATCH($E$4&"|"&$I$4&"|"&A89,_Story_AC_Recent!$A:$A,0)),"") | E89: =IFERROR(INDEX(_Story_AC_Recent!$H:$H,MATCH($E$4&"|"&$I$4&"|"&A89,_Story_AC_Recent!$A:$A,0)),"") | F89: =IFERROR(INDEX(_Story_AC_Recent!$J:$J,MATCH($E$4&"|"&$I$4&"|"&A89,_Story_AC_Recent!$A:$A,0)),"") | G89: =IFERROR(INDEX(_Story_AC_Recent!$K:$K,MATCH($E$4&"|"&$I$4&"|"&A89,_Story_AC_Recent!$A:$A,0)),"") | H89: =IFERROR(INDEX(_Story_AC_Recent!$L:$L,MATCH($E$4&"|"&$I$4&"|"&A89,_Story_AC_Recent!$A:$A,0)),"")
A90: 6 | B90: =IFERROR(INDEX(_Story_AC_Recent!$E:$E,MATCH($E$4&"|"&$I$4&"|"&A90,_Story_AC_Recent!$A:$A,0)),"") | C90: =IFERROR(INDEX(_Story_AC_Recent!$F:$F,MATCH($E$4&"|"&$I$4&"|"&A90,_Story_AC_Recent!$A:$A,0)),"") | D90: =IFERROR(INDEX(_Story_AC_Recent!$G:$G,MATCH($E$4&"|"&$I$4&"|"&A90,_Story_AC_Recent!$A:$A,0)),"") | E90: =IFERROR(INDEX(_Story_AC_Recent!$H:$H,MATCH($E$4&"|"&$I$4&"|"&A90,_Story_AC_Recent!$A:$A,0)),"") | F90: =IFERROR(INDEX(_Story_AC_Recent!$J:$J,MATCH($E$4&"|"&$I$4&"|"&A90,_Story_AC_Recent!$A:$A,0)),"") | G90: =IFERROR(INDEX(_Story_AC_Recent!$K:$K,MATCH($E$4&"|"&$I$4&"|"&A90,_Story_AC_Recent!$A:$A,0)),"") | H90: =IFERROR(INDEX(_Story_AC_Recent!$L:$L,MATCH($E$4&"|"&$I$4&"|"&A90,_Story_AC_Recent!$A:$A,0)),"")
A91: 7 | B91: =IFERROR(INDEX(_Story_AC_Recent!$E:$E,MATCH($E$4&"|"&$I$4&"|"&A91,_Story_AC_Recent!$A:$A,0)),"") | C91: =IFERROR(INDEX(_Story_AC_Recent!$F:$F,MATCH($E$4&"|"&$I$4&"|"&A91,_Story_AC_Recent!$A:$A,0)),"") | D91: =IFERROR(INDEX(_Story_AC_Recent!$G:$G,MATCH($E$4&"|"&$I$4&"|"&A91,_Story_AC_Recent!$A:$A,0)),"") | E91: =IFERROR(INDEX(_Story_AC_Recent!$H:$H,MATCH($E$4&"|"&$I$4&"|"&A91,_Story_AC_Recent!$A:$A,0)),"") | F91: =IFERROR(INDEX(_Story_AC_Recent!$J:$J,MATCH($E$4&"|"&$I$4&"|"&A91,_Story_AC_Recent!$A:$A,0)),"") | G91: =IFERROR(INDEX(_Story_AC_Recent!$K:$K,MATCH($E$4&"|"&$I$4&"|"&A91,_Story_AC_Recent!$A:$A,0)),"") | H91: =IFERROR(INDEX(_Story_AC_Recent!$L:$L,MATCH($E$4&"|"&$I$4&"|"&A91,_Story_AC_Recent!$A:$A,0)),"")
A92: 8 | B92: =IFERROR(INDEX(_Story_AC_Recent!$E:$E,MATCH($E$4&"|"&$I$4&"|"&A92,_Story_AC_Recent!$A:$A,0)),"") | C92: =IFERROR(INDEX(_Story_AC_Recent!$F:$F,MATCH($E$4&"|"&$I$4&"|"&A92,_Story_AC_Recent!$A:$A,0)),"") | D92: =IFERROR(INDEX(_Story_AC_Recent!$G:$G,MATCH($E$4&"|"&$I$4&"|"&A92,_Story_AC_Recent!$A:$A,0)),"") | E92: =IFERROR(INDEX(_Story_AC_Recent!$H:$H,MATCH($E$4&"|"&$I$4&"|"&A92,_Story_AC_Recent!$A:$A,0)),"") | F92: =IFERROR(INDEX(_Story_AC_Recent!$J:$J,MATCH($E$4&"|"&$I$4&"|"&A92,_Story_AC_Recent!$A:$A,0)),"") | G92: =IFERROR(INDEX(_Story_AC_Recent!$K:$K,MATCH($E$4&"|"&$I$4&"|"&A92,_Story_AC_Recent!$A:$A,0)),"") | H92: =IFERROR(INDEX(_Story_AC_Recent!$L:$L,MATCH($E$4&"|"&$I$4&"|"&A92,_Story_AC_Recent!$A:$A,0)),"")
A93: 9 | B93: =IFERROR(INDEX(_Story_AC_Recent!$E:$E,MATCH($E$4&"|"&$I$4&"|"&A93,_Story_AC_Recent!$A:$A,0)),"") | C93: =IFERROR(INDEX(_Story_AC_Recent!$F:$F,MATCH($E$4&"|"&$I$4&"|"&A93,_Story_AC_Recent!$A:$A,0)),"") | D93: =IFERROR(INDEX(_Story_AC_Recent!$G:$G,MATCH($E$4&"|"&$I$4&"|"&A93,_Story_AC_Recent!$A:$A,0)),"") | E93: =IFERROR(INDEX(_Story_AC_Recent!$H:$H,MATCH($E$4&"|"&$I$4&"|"&A93,_Story_AC_Recent!$A:$A,0)),"") | F93: =IFERROR(INDEX(_Story_AC_Recent!$J:$J,MATCH($E$4&"|"&$I$4&"|"&A93,_Story_AC_Recent!$A:$A,0)),"") | G93: =IFERROR(INDEX(_Story_AC_Recent!$K:$K,MATCH($E$4&"|"&$I$4&"|"&A93,_Story_AC_Recent!$A:$A,0)),"") | H93: =IFERROR(INDEX(_Story_AC_Recent!$L:$L,MATCH($E$4&"|"&$I$4&"|"&A93,_Story_AC_Recent!$A:$A,0)),"")
A94: 10 | B94: =IFERROR(INDEX(_Story_AC_Recent!$E:$E,MATCH($E$4&"|"&$I$4&"|"&A94,_Story_AC_Recent!$A:$A,0)),"") | C94: =IFERROR(INDEX(_Story_AC_Recent!$F:$F,MATCH($E$4&"|"&$I$4&"|"&A94,_Story_AC_Recent!$A:$A,0)),"") | D94: =IFERROR(INDEX(_Story_AC_Recent!$G:$G,MATCH($E$4&"|"&$I$4&"|"&A94,_Story_AC_Recent!$A:$A,0)),"") | E94: =IFERROR(INDEX(_Story_AC_Recent!$H:$H,MATCH($E$4&"|"&$I$4&"|"&A94,_Story_AC_Recent!$A:$A,0)),"") | F94: =IFERROR(INDEX(_Story_AC_Recent!$J:$J,MATCH($E$4&"|"&$I$4&"|"&A94,_Story_AC_Recent!$A:$A,0)),"") | G94: =IFERROR(INDEX(_Story_AC_Recent!$K:$K,MATCH($E$4&"|"&$I$4&"|"&A94,_Story_AC_Recent!$A:$A,0)),"") | H94: =IFERROR(INDEX(_Story_AC_Recent!$L:$L,MATCH($E$4&"|"&$I$4&"|"&A94,_Story_AC_Recent!$A:$A,0)),"")

Sheet Analyse_filtrable
A1: Détection | B1: Début fenêtre | C1: Ticket ID | D1: Key | E1: Sprint | F1: Statut | G1: Type | H1: Champ modifié | I1: Type de modification | J1: Projet | K1: Assigné | L1: Priorité | M1: Valeur avant | N1: Valeur après | O1: Extrait avant | P1: Extrait après | Q1: Lien | R1: Fichier précédent | S1: Fichier courant | T1: Jira updated après
A2: 46181.338 | B2: 46178.648 | C2: 392738 | D2: PPMG-1549 | E2: Sprint 17 2026 | F2: In Refinement | G2: Story | H2: Assigné | I2: Assigné modifié | J2: PPMG | K2: Patrick PONCET | L2: High | M2: Yosra MANAI | N2: Patrick PONCET | O2: Yosra MANAI | P2: Patrick PONCET | Q2: https://data-servier.atlassian.net/browse/PPMG-1549 | R2: ticket non clot (Jira)(2).xml | S2: ticket non clot (Jira)(3).xml | T2: 46178.662
A3: 46181.338 | B3: 46178.648 | C3: 392738 | D3: PPMG-1549 | E3: Sprint 17 2026 | F3: In Refinement | G3: Story | H3: Commentaires | I3: Commentaires modifiés | J3: PPMG | K3: Patrick PONCET | L3: High | M3: 4 | N3: 4 | O3: 4 | P3: 4 | Q3: https://data-servier.atlassian.net/browse/PPMG-1549 | R3: ticket non clot (Jira)(2).xml | S3: ticket non clot (Jira)(3).xml | T3: 46178.662
A4: 46181.338 | B4: 46178.648 | C4: 392738 | D4: PPMG-1549 | E4: Sprint 17 2026 | F4: In Refinement | G4: Story | H4: Custom fields | I4: Custom fields modifiés | J4: PPMG | K4: Patrick PONCET | L4: High | M4: Rank | N4: Rank | O4: Rank | P4: Rank | Q4: https://data-servier.atlassian.net/browse/PPMG-1549 | R4: ticket non clot (Jira)(2).xml | S4: ticket non clot (Jira)(3).xml | T4: 46178.662
A5: 46181.338 | B5: 46178.648 | C5: 392738 | D5: PPMG-1549 | E5: Sprint 17 2026 | F5: In Refinement | G5: Story | H5: Statut | I5: Statut modifié | J5: PPMG | K5: Patrick PONCET | L5: High | M5: Analyse | N5: In Refinement | O5: Analyse | P5: In Refinement | Q5: https://data-servier.atlassian.net/browse/PPMG-1549 | R5: ticket non clot (Jira)(2).xml | S5: ticket non clot (Jira)(3).xml | T5: 46178.662

Sheet Listes_filtres
A1: Sprint | B1: Statut | C1: Type | D1: Champ | E1: Projet
A2: Tous | B2: Tous | C2: Tous | D2: Tous | E2: Tous
A3: Sprint 17 2026 | B3: In Refinement | C3: Story | D3: Assigné | E3: PPMG
D4: Commentaires
D5: Custom fields
D6: Statut

Sheet _Story_AC_Lists
A1: Sprint | B1: Statut
A2: Tous | B2: Tous
A3: Sprint 10; Sprint 17 2026 | B3: Analyse
A4: Sprint 14 2026; Sprint 15 2026 | B4: Backlog
A5: Sprint 15 2026 | B5: Candidate
A6: Sprint 17 2026 | B6: Dev in Progress
B7: Go Prod
B8: In Refinement
B9: Ready for Development

Sheet _Story_AC_KPI
A1: Key | B1: Sprint | C1: Statut | D1: Stories dernier export | E1: Tickets Story impactés | F1: Total modifications | G1: Descriptions modifiées | H1: AC modifiés | I1: Tickets desc modifiée | J1: Tickets AC modifiés | K1: Tickets desc+AC | L1: Taux impact | M1: Première détection | N1: Dernière détection
A2: Tous|Tous | B2: Tous | C2: Tous | D2: 61 | E2: 0 | F2: 0 | G2: 0 | H2: 0 | I2: 0 | J2: 0 | K2: 0 | L2: 0
A3: Tous|Analyse | B3: Tous | C3: Analyse | D3: 4 | E3: 0 | F3: 0 | G3: 0 | H3: 0 | I3: 0 | J3: 0 | K3: 0 | L3: 0
A4: Tous|Backlog | B4: Tous | C4: Backlog | D4: 40 | E4: 0 | F4: 0 | G4: 0 | H4: 0 | I4: 0 | J4: 0 | K4: 0 | L4: 0
A5: Tous|Candidate | B5: Tous | C5: Candidate | D5: 1 | E5: 0 | F5: 0 | G5: 0 | H5: 0 | I5: 0 | J5: 0 | K5: 0 | L5: 0
A6: Tous|Dev in Progress | B6: Tous | C6: Dev in Progress | D6: 1 | E6: 0 | F6: 0 | G6: 0 | H6: 0 | I6: 0 | J6: 0 | K6: 0 | L6: 0
A7: Tous|Go Prod | B7: Tous | C7: Go Prod | D7: 1 | E7: 0 | F7: 0 | G7: 0 | H7: 0 | I7: 0 | J7: 0 | K7: 0 | L7: 0
A8: Tous|In Refinement | B8: Tous | C8: In Refinement | D8: 1 | E8: 0 | F8: 0 | G8: 0 | H8: 0 | I8: 0 | J8: 0 | K8: 0 | L8: 0
A9: Tous|Ready for Development | B9: Tous | C9: Ready for Development | D9: 13 | E9: 0 | F9: 0 | G9: 0 | H9: 0 | I9: 0 | J9: 0 | K9: 0 | L9: 0
A10: Sprint 10; Sprint 17 2026|Tous | B10: Sprint 10; Sprint 17 2026 | C10: Tous | D10: 1 | E10: 0 | F10: 0 | G10: 0 | H10: 0 | I10: 0 | J10: 0 | K10: 0 | L10: 0
A11: Sprint 10; Sprint 17 2026|Analyse | B11: Sprint 10; Sprint 17 2026 | C11: Analyse | D11: 1 | E11: 0 | F11: 0 | G11: 0 | H11: 0 | I11: 0 | J11: 0 | K11: 0 | L11: 0
A12: Sprint 10; Sprint 17 2026|Backlog | B12: Sprint 10; Sprint 17 2026 | C12: Backlog | D12: 0 | E12: 0 | F12: 0 | G12: 0 | H12: 0 | I12: 0 | J12: 0 | K12: 0 | L12: 0
A13: Sprint 10; Sprint 17 2026|Candidate | B13: Sprint 10; Sprint 17 2026 | C13: Candidate | D13: 0 | E13: 0 | F13: 0 | G13: 0 | H13: 0 | I13: 0 | J13: 0 | K13: 0 | L13: 0
... A41: Sprint 17 2026|Ready for Development | B41: Sprint 17 2026 | C41: Ready for Development | D41: 12 | E41: 0 | F41: 0 | G41: 0 | H41: 0 | I41: 0 | J41: 0 | K41: 0 | L41: 0

Sheet _Story_AC_Field
A1: Key | B1: Sprint | C1: Statut | D1: Champ | E1: Modifications | F1: Tickets concernés
A2: Tous|Tous|Description | B2: Tous | C2: Tous | D2: Description | E2: 0 | F2: 0
A3: Tous|Tous|Acceptance Criteria | B3: Tous | C3: Tous | D3: Acceptance Criteria | E3: 0 | F3: 0
A4: Tous|Analyse|Description | B4: Tous | C4: Analyse | D4: Description | E4: 0 | F4: 0
A5: Tous|Analyse|Acceptance Criteria | B5: Tous | C5: Analyse | D5: Acceptance Criteria | E5: 0 | F5: 0
A6: Tous|Backlog|Description | B6: Tous | C6: Backlog | D6: Description | E6: 0 | F6: 0
A7: Tous|Backlog|Acceptance Criteria | B7: Tous | C7: Backlog | D7: Acceptance Criteria | E7: 0 | F7: 0
A8: Tous|Candidate|Description | B8: Tous | C8: Candidate | D8: Description | E8: 0 | F8: 0
A9: Tous|Candidate|Acceptance Criteria | B9: Tous | C9: Candidate | D9: Acceptance Criteria | E9: 0 | F9: 0
A10: Tous|Dev in Progress|Description | B10: Tous | C10: Dev in Progress | D10: Description | E10: 0 | F10: 0
A11: Tous|Dev in Progress|Acceptance Criteria | B11: Tous | C11: Dev in Progress | D11: Acceptance Criteria | E11: 0 | F11: 0
A12: Tous|Go Prod|Description | B12: Tous | C12: Go Prod | D12: Description | E12: 0 | F12: 0
A13: Tous|Go Prod|Acceptance Criteria | B13: Tous | C13: Go Prod | D13: Acceptance Criteria | E13: 0 | F13: 0
... A81: Sprint 17 2026|Ready for Development|Acceptance Criteria | B81: Sprint 17 2026 | C81: Ready for Development | D81: Acceptance Criteria | E81: 0 | F81: 0

Sheet _Story_AC_Evo
A1: Key | B1: Sprint | C1: Statut | D1: Date clé | E1: Descriptions modifiées | F1: AC modifiés | G1: Tickets impactés
A2: Tous|Tous|2026-06-08 08:07:02 UTC | B2: Tous | C2: Tous | D2: 2026-06-08 08:07:02 UTC | E2: 0 | F2: 0 | G2: 0
A3: Tous|Analyse|2026-06-08 08:07:02 UTC | B3: Tous | C3: Analyse | D3: 2026-06-08 08:07:02 UTC | E3: 0 | F3: 0 | G3: 0
A4: Tous|Backlog|2026-06-08 08:07:02 UTC | B4: Tous | C4: Backlog | D4: 2026-06-08 08:07:02 UTC | E4: 0 | F4: 0 | G4: 0
A5: Tous|Candidate|2026-06-08 08:07:02 UTC | B5: Tous | C5: Candidate | D5: 2026-06-08 08:07:02 UTC | E5: 0 | F5: 0 | G5: 0
A6: Tous|Dev in Progress|2026-06-08 08:07:02 UTC | B6: Tous | C6: Dev in Progress | D6: 2026-06-08 08:07:02 UTC | E6: 0 | F6: 0 | G6: 0
A7: Tous|Go Prod|2026-06-08 08:07:02 UTC | B7: Tous | C7: Go Prod | D7: 2026-06-08 08:07:02 UTC | E7: 0 | F7: 0 | G7: 0
A8: Tous|In Refinement|2026-06-08 08:07:02 UTC | B8: Tous | C8: In Refinement | D8: 2026-06-08 08:07:02 UTC | E8: 0 | F8: 0 | G8: 0
A9: Tous|Ready for Development|2026-06-08 08:07:02 UTC | B9: Tous | C9: Ready for Development | D9: 2026-06-08 08:07:02 UTC | E9: 0 | F9: 0 | G9: 0
A10: Sprint 10; Sprint 17 2026|Tous|2026-06-08 08:07:02 UTC | B10: Sprint 10; Sprint 17 2026 | C10: Tous | D10: 2026-06-08 08:07:02 UTC | E10: 0 | F10: 0 | G10: 0
A11: Sprint 10; Sprint 17 2026|Analyse|2026-06-08 08:07:02 UTC | B11: Sprint 10; Sprint 17 2026 | C11: Analyse | D11: 2026-06-08 08:07:02 UTC | E11: 0 | F11: 0 | G11: 0
A12: Sprint 10; Sprint 17 2026|Backlog|2026-06-08 08:07:02 UTC | B12: Sprint 10; Sprint 17 2026 | C12: Backlog | D12: 2026-06-08 08:07:02 UTC | E12: 0 | F12: 0 | G12: 0
A13: Sprint 10; Sprint 17 2026|Candidate|2026-06-08 08:07:02 UTC | B13: Sprint 10; Sprint 17 2026 | C13: Candidate | D13: 2026-06-08 08:07:02 UTC | E13: 0 | F13: 0 | G13: 0
... A41: Sprint 17 2026|Ready for Development|2026-06-08 08:07:02 UTC | B41: Sprint 17 2026 | C41: Ready for Development | D41: 2026-06-08 08:07:02 UTC | E41: 0 | F41: 0 | G41: 0

Sheet _Story_AC_Top
A1: Key | B1: Sprint | C1: Statut | D1: Rang | E1: Ticket ID | F1: Jira key | G1: Résumé | H1: Statut ticket | I1: Description | J1: AC | K1: Total | L1: Dernière détection | M1: Lien

Sheet _Story_AC_Recent
A1: Key | B1: Sprint | C1: Statut | D1: Rang | E1: Détection | F1: Jira key | G1: Champ | H1: Statut ticket | I1: Sprint ticket | J1: Extrait avant | K1: Extrait après | L1: Lien | M1: Résumé

Sheet Modifications_focus
A1: Fenêtre début | B1: Fenêtre fin / détection | C1: Fichier précédent | D1: Fichier courant | E1: Ticket ID | F1: Key avant | G1: Key après | H1: Projet | I1: Sprint avant | J1: Sprint après | K1: Sprint effectif | L1: Statut avant | M1: Statut après | N1: Statut effectif | O1: Catégorie statut avant | P1: Catégorie statut après | Q1: Type avant | R1: Type après | S1: Type effectif | T1: Assigné avant | U1: Assigné après | V1: Priorité avant | W1: Priorité après | X1: Champ modifié | Y1: Type de modification | Z1: Valeur avant | AA1: Valeur après | AB1: Taille avant | AC1: Taille après | AD1: Extrait avant | AE1: Extrait après | AF1: Jira updated avant | AG1: Jira updated après | AH1: Lien
A2: 46178.648 | B2: 46181.338 | C2: ticket non clot (Jira)(2).xml | D2: ticket non clot (Jira)(3).xml | E2: 392738 | F2: PPMG-1549 | G2: PPMG-1549 | H2: PPMG | I2: Sprint 17 2026 | J2: Sprint 17 2026 | K2: Sprint 17 2026 | L2: Analyse | M2: In Refinement | N2: In Refinement | O2: indeterminate | P2: indeterminate | Q2: Story | R2: Story | S2: Story | T2: Yosra MANAI | U2: Patrick PONCET | V2: High | W2: High | X2: Statut | Y2: Statut modifié | Z2: Analyse | AA2: In Refinement | AB2: 7 | AC2: 13 | AD2: Analyse | AE2: In Refinement | AF2: 46178.545 | AG2: 46178.662 | AH2: https://data-servier.atlassian.net/browse/PPMG-1549
A3: 46178.648 | B3: 46181.338 | C3: ticket non clot (Jira)(2).xml | D3: ticket non clot (Jira)(3).xml | E3: 392738 | F3: PPMG-1549 | G3: PPMG-1549 | H3: PPMG | I3: Sprint 17 2026 | J3: Sprint 17 2026 | K3: Sprint 17 2026 | L3: Analyse | M3: In Refinement | N3: In Refinement | O3: indeterminate | P3: indeterminate | Q3: Story | R3: Story | S3: Story | T3: Yosra MANAI | U3: Patrick PONCET | V3: High | W3: High | X3: Assigné | Y3: Assigné modifié | Z3: Yosra MANAI | AA3: Patrick PONCET | AB3: 11 | AC3: 14 | AD3: Yosra MANAI | AE3: Patrick PONCET | AF3: 46178.545 | AG3: 46178.662 | AH3: https://data-servier.atlassian.net/browse/PPMG-1549
A4: 46178.648 | B4: 46181.338 | C4: ticket non clot (Jira)(2).xml | D4: ticket non clot (Jira)(3).xml | E4: 392738 | F4: PPMG-1549 | G4: PPMG-1549 | H4: PPMG | I4: Sprint 17 2026 | J4: Sprint 17 2026 | K4: Sprint 17 2026 | L4: Analyse | M4: In Refinement | N4: In Refinement | O4: indeterminate | P4: indeterminate | Q4: Story | R4: Story | S4: Story | T4: Yosra MANAI | U4: Patrick PONCET | V4: High | W4: High | X4: Commentaires | Y4: Commentaires modifiés | Z4: 4 | AA4: 4 | AB4: 4 | AC4: 4 | AD4: 4 | AE4: 4 | AF4: 46178.545 | AG4: 46178.662 | AH4: https://data-servier.atlassian.net/browse/PPMG-1549
A5: 46178.648 | B5: 46181.338 | C5: ticket non clot (Jira)(2).xml | D5: ticket non clot (Jira)(3).xml | E5: 392738 | F5: PPMG-1549 | G5: PPMG-1549 | H5: PPMG | I5: Sprint 17 2026 | J5: Sprint 17 2026 | K5: Sprint 17 2026 | L5: Analyse | M5: In Refinement | N5: In Refinement | O5: indeterminate | P5: indeterminate | Q5: Story | R5: Story | S5: Story | T5: Yosra MANAI | U5: Patrick PONCET | V5: High | W5: High | X5: Custom fields | Y5: Custom fields modifiés | Z5: Rank | AA5: Rank | AB5: 1 | AC5: 1 | AD5: Rank | AE5: Rank | AF5: 46178.545 | AG5: 46178.662 | AH5: https://data-servier.atlassian.net/browse/PPMG-1549

Sheet Modifications_toutes
A1: Fenêtre début | B1: Fenêtre fin / détection | C1: Fichier précédent | D1: Fichier courant | E1: Ticket ID | F1: Key avant | G1: Key après | H1: Projet | I1: Sprint avant | J1: Sprint après | K1: Sprint effectif | L1: Statut avant | M1: Statut après | N1: Statut effectif | O1: Catégorie statut avant | P1: Catégorie statut après | Q1: Type avant | R1: Type après | S1: Type effectif | T1: Assigné avant | U1: Assigné après | V1: Priorité avant | W1: Priorité après | X1: Champ modifié | Y1: Type de modification | Z1: Valeur avant | AA1: Valeur après | AB1: Taille avant | AC1: Taille après | AD1: Extrait avant | AE1: Extrait après | AF1: Jira updated avant | AG1: Jira updated après | AH1: Lien
A2: 46178.648 | B2: 46181.338 | C2: ticket non clot (Jira)(2).xml | D2: ticket non clot (Jira)(3).xml | E2: 392738 | F2: PPMG-1549 | G2: PPMG-1549 | H2: PPMG | I2: Sprint 17 2026 | J2: Sprint 17 2026 | K2: Sprint 17 2026 | L2: Analyse | M2: In Refinement | N2: In Refinement | O2: indeterminate | P2: indeterminate | Q2: Story | R2: Story | S2: Story | T2: Yosra MANAI | U2: Patrick PONCET | V2: High | W2: High | X2: Statut | Y2: Statut modifié | Z2: Analyse | AA2: In Refinement | AB2: 7 | AC2: 13 | AD2: Analyse | AE2: In Refinement | AF2: 46178.545 | AG2: 46178.662 | AH2: https://data-servier.atlassian.net/browse/PPMG-1549
A3: 46178.648 | B3: 46181.338 | C3: ticket non clot (Jira)(2).xml | D3: ticket non clot (Jira)(3).xml | E3: 392738 | F3: PPMG-1549 | G3: PPMG-1549 | H3: PPMG | I3: Sprint 17 2026 | J3: Sprint 17 2026 | K3: Sprint 17 2026 | L3: Analyse | M3: In Refinement | N3: In Refinement | O3: indeterminate | P3: indeterminate | Q3: Story | R3: Story | S3: Story | T3: Yosra MANAI | U3: Patrick PONCET | V3: High | W3: High | X3: Assigné | Y3: Assigné modifié | Z3: Yosra MANAI | AA3: Patrick PONCET | AB3: 11 | AC3: 14 | AD3: Yosra MANAI | AE3: Patrick PONCET | AF3: 46178.545 | AG3: 46178.662 | AH3: https://data-servier.atlassian.net/browse/PPMG-1549
A4: 46178.648 | B4: 46181.338 | C4: ticket non clot (Jira)(2).xml | D4: ticket non clot (Jira)(3).xml | E4: 392738 | F4: PPMG-1549 | G4: PPMG-1549 | H4: PPMG | I4: Sprint 17 2026 | J4: Sprint 17 2026 | K4: Sprint 17 2026 | L4: Analyse | M4: In Refinement | N4: In Refinement | O4: indeterminate | P4: indeterminate | Q4: Story | R4: Story | S4: Story | T4: Yosra MANAI | U4: Patrick PONCET | V4: High | W4: High | X4: Commentaires | Y4: Commentaires modifiés | Z4: 4 | AA4: 4 | AB4: 4 | AC4: 4 | AD4: 4 | AE4: 4 | AF4: 46178.545 | AG4: 46178.662 | AH4: https://data-servier.atlassian.net/browse/PPMG-1549
A5: 46178.648 | B5: 46181.338 | C5: ticket non clot (Jira)(2).xml | D5: ticket non clot (Jira)(3).xml | E5: 392738 | F5: PPMG-1549 | G5: PPMG-1549 | H5: PPMG | I5: Sprint 17 2026 | J5: Sprint 17 2026 | K5: Sprint 17 2026 | L5: Analyse | M5: In Refinement | N5: In Refinement | O5: indeterminate | P5: indeterminate | Q5: Story | R5: Story | S5: Story | T5: Yosra MANAI | U5: Patrick PONCET | V5: High | W5: High | X5: Custom fields | Y5: Custom fields modifiés | Z5: Rank | AA5: Rank | AB5: 1 | AC5: 1 | AD5: Rank | AE5: Rank | AF5: 46178.545 | AG5: 46178.662 | AH5: https://data-servier.atlassian.net/browse/PPMG-1549

Sheet KPI_fenetres
A1: Fenêtre début | B1: Fenêtre fin / détection | C1: Fichier précédent | D1: Fichier courant | E1: Tickets modifiés | F1: Total modifications | G1: Descriptions modifiées | H1: AC modifiés | I1: Changements statut | J1: Changements sprint | K1: Commentaires ajoutés/modifiés | L1: Tickets apparus | M1: Tickets disparus
A2: 46178.648 | B2: 46181.338 | C2: ticket non clot (Jira)(2).xml | D2: ticket non clot (Jira)(3).xml | E2: 1 | F2: 4 | G2: 0 | H2: 0 | I2: 1 | J2: 0 | K2: 1 | L2: 0 | M2: 0

Sheet KPI_sprint_status
A1: Sprint | B1: Statut | C1: Type | D1: Champ modifié | E1: Modifications | F1: Tickets concernés
A2: Sprint 17 2026 | B2: In Refinement | C2: Story | D2: Assigné | E2: 1 | F2: 1
A3: Sprint 17 2026 | B3: In Refinement | C3: Story | D3: Commentaires | E3: 1 | F3: 1
A4: Sprint 17 2026 | B4: In Refinement | C4: Story | D4: Custom fields | E4: 1 | F4: 1
A5: Sprint 17 2026 | B5: In Refinement | C5: Story | D5: Statut | E5: 1 | F5: 1

Sheet Descriptions_modifiees
A1: Aucune donnée

Sheet AC_modifies
A1: Aucune donnée

Sheet Story_Desc_AC_events
A1: Aucune donnée

Sheet Lifecycle
A1: Aucune donnée

Sheet Top_tickets
A1: Ticket ID | B1: Key | C1: Projet | D1: Sprint effectif | E1: Statut effectif | F1: Type effectif | G1: Assigné | H1: Modifications | I1: Champs modifiés | J1: Première détection | K1: Dernière détection | L1: Lien
A2: 392738 | B2: PPMG-1549 | C2: PPMG | D2: Sprint 17 2026 | E2: In Refinement | F2: Story | G2: Patrick PONCET | H2: 4 | I2: Assigné; Commentaires; Custom fields; Statut | J2: 46181.338 | K2: 46181.338 | L2: https://data-servier.atlassian.net/browse/PPMG-1549

Sheet Snapshots
A1: Ordre | B1: Date export | C1: Date source | D1: Fichier | E1: Chemin | F1: Tickets | G1: Warnings
A2: 1 | B2: 46178.648 | C2: Fri Jun 05 15:33:16 UTC 2026 | D2: ticket non clot (Jira)(2).xml | E2: C:\Users\ciesl\Downloads\rss chrono\ticket non clot (Jira)(2).xml | F2: 176
A3: 2 | B3: 46181.338 | C3: Mon Jun 08 08:07:02 UTC 2026 | D3: ticket non clot (Jira)(3).xml | E3: C:\Users\ciesl\Downloads\rss chrono\ticket non clot (Jira)(3).xml | F3: 176

Sheet Latest_snapshot
A1: Ticket ID | B1: Key | C1: Projet | D1: Sprint | E1: Statut | F1: Catégorie statut | G1: Type | H1: Priorité | I1: Assigné | J1: Résumé | K1: Created | L1: Updated | M1: Âge jours | N1: Jours depuis update | O1: AC présent | P1: Source AC | Q1: Commentaires | R1: Pièces jointes | S1: Liens Jira | T1: Lien
A2: 169929 | B2: PPMG-1027 | C2: PPMG | E2: Candidate | F2: new | G2: Change | H2: Low | I2: Grégory RUGET | J2: [Gestion budgétaire V2-P1] Modification de l'option "View > Grouping elements" | K2: 45573.371 | L2: 45833.337 | M2: 607.97 | N2: 348 | O2: TRUE | P2: customfield: Acceptance Criteria | Q2: 5 | R2: 0 | S2: 2 | T2: https://data-servier.atlassian.net/browse/PPMG-1027
A3: 224092 | B3: PPMG-1193 | C3: PPMG | D3: Sprint 17 2026 | E3: En cours | F3: indeterminate | G3: Tâche | H3: Highest | I3: Pierre KAYA | J3: [A TESTER Servier] Test nouvelle version interface ACTIVITY-VYP | K3: 45754.419 | L3: 46148.333 | M3: 426.92 | N3: 33.01 | O3: FALSE | P3: missing | Q3: 8 | R3: 0 | S3: 1 | T3: https://data-servier.atlassian.net/browse/PPMG-1193
A4: 225874 | B4: PPMG-1197 | C4: PPMG | E4: Backlog | F4: new | G4: Change | H4: Medium | I4: Yassine BOUARI | J4: [Tous les Champs texte enrichi] Taille de police par défaut (OTD 177189) | K4: 45756.823 | L4: 45756.826 | M4: 424.51 | N4: 424.51 | O4: FALSE | P4: missing | Q4: 4 | R4: 1 | S4: 1 | T4: https://data-servier.atlassian.net/browse/PPMG-1197
A5: 230390 | B5: PPMG-1205 | C5: PPMG | E5: Backlog | F5: new | G5: Story | H5: Highest | I5: Patrick PONCET | J5: Analyse techniquo fonctionnel pour l'utilisation des budgets lines | K5: 45770.574 | L5: 46078.398 | M5: 410.76 | N5: 102.94 | O5: TRUE | P5: customfield: Acceptance Criteria | Q5: 6 | R5: 0 | S5: 0 | T5: https://data-servier.atlassian.net/browse/PPMG-1205
A6: 250815 | B6: PPMG-1222 | C6: PPMG | E6: Backlog | F6: new | G6: Story | H6: High | I6: RACHEL CLOIX | J6: Définir un nombre maximum de caractères pour les champs texte riche. | K6: 45804.499 | L6: 46129.351 | M6: 376.84 | N6: 51.99 | O6: TRUE | P6: customfield: Acceptance Criteria | Q6: 7 | R6: 0 | S6: 0 | T6: https://data-servier.atlassian.net/browse/PPMG-1222
A7: 250970 | B7: PPMG-1227 | C7: PPMG | E7: Backlog | F7: new | G7: Change | H7: Medium | I7: Grégory RUGET | J7: [Risques] gestion du Mitigation Plan | K7: 45805.281 | L7: 46127.348 | M7: 376.06 | N7: 53.99 | O7: TRUE | P7: description: expected/acceptance markers | Q7: 3 | R7: 0 | S7: 0 | T7: https://data-servier.atlassian.net/browse/PPMG-1227
A8: 250974 | B8: PPMG-1229 | C8: PPMG | E8: Backlog | F8: new | G8: Change | H8: Medium | I8: Typhaine MICHEL | J8: [Issues] Plan d'action | K8: 45805.286 | L8: 46127.349 | M8: 376.05 | N8: 53.99 | O8: FALSE | P8: missing | Q8: 2 | R8: 0 | S8: 0 | T8: https://data-servier.atlassian.net/browse/PPMG-1229
A9: 250977 | B9: PPMG-1231 | C9: PPMG | E9: Dev in Progress | F9: indeterminate | G9: Change | H9: Medium | I9: Patrick PONCET | J9: [Gantt][ON HOLD PLW] OTD - 201933 Affichage par défaut | K9: 45805.291 | L9: 46092.384 | M9: 376.05 | N9: 88.95 | O9: FALSE | P9: missing | Q9: 4 | R9: 1 | S9: 0 | T9: https://data-servier.atlassian.net/browse/PPMG-1231
A10: 251034 | B10: PPMG-1233 | C10: PPMG | E10: Backlog | F10: new | G10: Change | H10: Medium | I10: Grégory RUGET | J10: [Risques] [Issues] Gestion des plan d'actions | K10: 45805.354 | L10: 46127.348 | M10: 375.98 | N10: 53.99 | O10: FALSE | P10: missing | Q10: 0 | R10: 0 | S10: 0 | T10: https://data-servier.atlassian.net/browse/PPMG-1233
A11: 252701 | B11: PPMG-1241 | C11: PPMG | D11: Sprint 15 2026 | E11: Backlog | F11: new | G11: Tâche | H11: Highest | I11: RACHEL CLOIX | J11: Identifier les couts/payroll/budget erronés sur une initiative | K11: 45812.603 | L11: 46113.51 | M11: 368.73 | N11: 67.83 | O11: TRUE | P11: customfield: Acceptance Criteria | Q11: 8 | R11: 0 | S11: 2 | T11: https://data-servier.atlassian.net/browse/PPMG-1241
A12: 258526 | B12: PPMG-1257 | C12: PPMG | E12: Backlog | F12: new | G12: Tâche | H12: Medium | I12: Hajar AIT MENDIL | J12: [INTERFACE LOG] - Intégrer la création de logs aux interfaces existantes | K12: 45833.5 | L12: 45833.5 | M12: 347.84 | N12: 347.84 | O12: FALSE | P12: missing | Q12: 0 | R12: 0 | S12: 0 | T12: https://data-servier.atlassian.net/browse/PPMG-1257
A13: 264567 | B13: PPMG-1268 | C13: PPMG | D13: Sprint 15 2026 | E13: Ready for Development | F13: new | G13: Change | H13: High | I13: Patrick PONCET | J13: [MDM] [Attribut] Department Lead Domain à rendre monovalué | K13: 45848.637 | L13: 46113.508 | M13: 332.7 | N13: 67.83 | O13: TRUE | P13: customfield: Acceptance Criteria | Q13: 4 | R13: 0 | S13: 0 | T13: https://data-servier.atlassian.net/browse/PPMG-1268
A14: 264788 | B14: PPMG-1269 | C14: PPMG | D14: Sprint 10; Sprint 17 2026 | E14: Analyse | F14: indeterminate | G14: Story | H14: Highest | I14: RACHEL CLOIX | J14: [Suite 2] - Interface DataPlatform - VYP : récupération des valeurs engagé, réalisé et temps passés de Pilot CT | K14: 45849.57 | L14: 46148.347 | M14: 331.77 | N14: 32.99 | O14: FALSE | P14: missing | Q14: 4 | R14: 0 | S14: 1 | T14: https://data-servier.atlassian.net/browse/PPMG-1269
A15: 306680 | B15: PPMG-1392 | C15: PPMG | D15: Sprint 15 2026 | E15: Dev in Progress | F15: indeterminate | G15: Story | H15: Highest | I15: Herve ONNO | J15: OTD - 212664 [INTERFACE VYP -> DP] - Mettre en place un nettoyage des fichiers SFTP | K15: 45933.637 | L15: 46162.322 | M15: 247.7 | N15: 19.02 | O15: TRUE | P15: customfield: Acceptance Criteria | Q15: 7 | R15: 1 | S15: 0 | T15: https://data-servier.atlassian.net/browse/PPMG-1392
A16: 307578 | B16: PPMG-1398 | C16: PPMG | E16: Backlog | F16: new | G16: Story | H16: High | I16: Grégory RUGET | J16: BrainstormingACI Amélioration - Amelioration workbox + home projet | K16: 45937.491 | L16: 45938.319 | M16: 243.85 | N16: 243.02 | O16: FALSE | P16: missing | Q16: 0 | R16: 0 | S16: 0 | T16: https://data-servier.atlassian.net/browse/PPMG-1398
A17: 307603 | B17: PPMG-1399 | C17: PPMG | E17: Backlog | F17: new | G17: Story | H17: High | I17: Grégory RUGET | J17: BrainstormingACI Amélioration - Indicateurs | K17: 45937.517 | L17: 45938.327 | M17: 243.82 | N17: 243.01 | O17: FALSE | P17: missing | Q17: 0 | R17: 0 | S17: 0 | T17: https://data-servier.atlassian.net/browse/PPMG-1399
A18: 307605 | B18: PPMG-1400 | C18: PPMG | E18: Backlog | F18: new | G18: Story | H18: High | I18: Grégory RUGET | J18: BrainstormingACI Amélioration - Interfaces et intégrations | K18: 45937.518 | L18: 45938.326 | M18: 243.82 | N18: 243.01 | O18: FALSE | P18: missing | Q18: 0 | R18: 0 | S18: 0 | T18: https://data-servier.atlassian.net/browse/PPMG-1400
A19: 307606 | B19: PPMG-1401 | C19: PPMG | E19: Backlog | F19: new | G19: Story | H19: High | I19: Grégory RUGET | J19: BrainstormingACI Amélioration - ID card et des dashboards | K19: 45937.519 | L19: 45938.325 | M19: 243.82 | N19: 243.01 | O19: FALSE | P19: missing | Q19: 0 | R19: 0 | S19: 0 | T19: https://data-servier.atlassian.net/browse/PPMG-1401
A20: 307607 | B20: PPMG-1402 | C20: PPMG | E20: Backlog | F20: new | G20: Story | H20: High | I20: Grégory RUGET | J20: BrainstormingACI Amélioration - Amelioration de l'organisation | K20: 45937.519 | L20: 45938.32 | M20: 243.82 | N20: 243.02 | O20: FALSE | P20: missing | Q20: 0 | R20: 0 | S20: 0 | T20: https://data-servier.atlassian.net/browse/PPMG-1402
A21: 309547 | B21: PPMG-1411 | C21: PPMG | D21: Sprint 17 2026 | E21: Analyse | F21: indeterminate | G21: Story | H21: Highest | I21: RACHEL CLOIX | J21: [INTERFACE - VYP -> DP R&D ] Export de la monthly baseline | K21: 45943.528 | L21: 46178.403 | M21: 237.81 | N21: 2.93 | O21: FALSE | P21: missing | Q21: 2 | R21: 0 | S21: 0 | T21: https://data-servier.atlassian.net/browse/PPMG-1411
A22: 316352 | B22: PPMG-1419 | C22: PPMG | D22: Sprint 13 2026; Sprint 14 2026; Sprint 15 2026 | E22: En cours | F22: indeterminate | G22: Tâche | H22: Medium | I22: RACHEL CLOIX | J22: Automatisation des notifications pour le nettoyage des licences inutilisées | K22: 45957.567 | L22: 46126.623 | M22: 223.77 | N22: 54.71 | O22: TRUE | P22: customfield: Acceptance Criteria | Q22: 0 | R22: 0 | S22: 0 | T22: https://data-servier.atlassian.net/browse/PPMG-1419
A23: 317409 | B23: PPMG-1425 | C23: PPMG | D23: Sprint 17 2026 | E23: Backlog | F23: new | G23: Story | H23: Lowest | I23: Typhaine MICHEL | J23: [Attributs] Modifications 3/3 | K23: 45959.561 | L23: 46175.414 | M23: 221.78 | N23: 5.92 | O23: TRUE | P23: customfield: Acceptance Criteria | Q23: 5 | R23: 0 | S23: 2 | T23: https://data-servier.atlassian.net/browse/PPMG-1425
A24: 318635 | B24: PPMG-1432 | C24: PPMG | D24: Sprint 14 2026; Sprint 15 2026 | E24: Analyse | F24: indeterminate | G24: Change | H24: High | I24: Typhaine MICHEL | J24: [Attributs] [Module Project] Champs date | K24: 45960.692 | L24: 46126.623 | M24: 220.65 | N24: 54.71 | O24: TRUE | P24: customfield: Acceptance Criteria | Q24: 1 | R24: 0 | S24: 1 | T24: https://data-servier.atlassian.net/browse/PPMG-1432
A25: 327987 | B25: PPMG-1440 | C25: PPMG | D25: Sprint 14 2026; Sprint 15 2026 | E25: Analyse | F25: indeterminate | G25: Story | H25: Medium | I25: Yosra MANAI | J25: [AMOA] [Gantt] Ajout de nouvelles librairies d'activité & Modification template standard | K25: 45987.293 | L25: 46153.432 | M25: 194.05 | N25: 27.91 | O25: FALSE | P25: missing | Q25: 3 | R25: 0 | S25: 0 | T25: https://data-servier.atlassian.net/browse/PPMG-1440
A26: 329131 | B26: PPMG-1446 | C26: PPMG | E26: Backlog | F26: new | G26: Story | H26: Medium | I26: Yassine BOUARI | J26: [R&D] - Etude de faisabilité - Reporting pour visualiser les Baselines | K26: 45989.37 | L26: 45992.483 | M26: 191.97 | N26: 188.85 | O26: FALSE | P26: missing | Q26: 0 | R26: 0 | S26: 0 | T26: https://data-servier.atlassian.net/browse/PPMG-1446
A27: 334862 | B27: PPMG-1454 | C27: PPMG | E27: Ready for Development | F27: new | G27: Change | H27: High | I27: Patrick PONCET | J27: [Value Business Case] VBC – Ajout d’un onglet de synthèse et évolutions associées | K27: 46002.447 | L27: 46090.403 | M27: 178.89 | N27: 90.94 | O27: TRUE | P27: customfield: Acceptance Criteria | Q27: 4 | R27: 1 | S27: 0 | T27: https://data-servier.atlassian.net/browse/PPMG-1454
A28: 334886 | B28: PPMG-1455 | C28: PPMG | E28: Backlog | F28: new | G28: Story | H28: Medium | I28: Non assigné | J28: Ne pas laisser la possibilité de modifier les lignes interfacées dans le module financier | K28: 46002.459 | L28: 46002.459 | M28: 178.88 | N28: 178.88 | O28: TRUE | P28: customfield: Acceptance Criteria | Q28: 0 | R28: 0 | S28: 0 | T28: https://data-servier.atlassian.net/browse/PPMG-1455
A29: 335765 | B29: PPMG-1459 | C29: PPMG | D29: Sprint 14 2026 | E29: Ouvert | F29: new | G29: Bug | H29: Highest | I29: Romain CIESLIK | J29: Règles de gestion sur le champ "Name" du projet | K29: 46006.43 | L29: 46133.411 | M29: 174.91 | N29: 47.93 | O29: TRUE | P29: customfield: Acceptance Criteria | Q29: 10 | R29: 1 | S29: 1 | T29: https://data-servier.atlassian.net/browse/PPMG-1459
A30: 337641 | B30: PPMG-1460 | C30: PPMG | E30: Backlog | F30: new | G30: Story | H30: Low | I30: RACHEL CLOIX | J30: [COST & LOAD] Afficher la vue consolidée (somme verticale) au niveau des regroupements | K30: 46007.687 | L30: 46078.412 | M30: 173.65 | N30: 102.93 | O30: FALSE | P30: missing | Q30: 3 | R30: 1 | S30: 0 | T30: https://data-servier.atlassian.net/browse/PPMG-1460
A31: 337646 | B31: PPMG-1461 | C31: PPMG | E31: Backlog | F31: new | G31: Story | H31: Medium | I31: RACHEL CLOIX | J31: [STAGE & GATE] Ajouter le commentaire obligatoire du passage de gate dans un reporting | K31: 46007.689 | L31: 46106.393 | M31: 173.65 | N31: 74.94 | O31: FALSE | P31: missing | Q31: 1 | R31: 0 | S31: 0 | T31: https://data-servier.atlassian.net/browse/PPMG-1461
A32: 339819 | B32: PPMG-1470 | C32: PPMG | E32: Backlog | F32: new | G32: Tâche | H32: Medium | I32: Non assigné | J32: [SFTP] Accès aux fichiers sur le serveur SFTP OTD 205560 | K32: 46014.622 | L32: 46014.622 | M32: 166.72 | N32: 166.72 | O32: FALSE | P32: missing | Q32: 0 | R32: 0 | S32: 0 | T32: https://data-servier.atlassian.net/browse/PPMG-1470
A33: 342620 | B33: PPMG-1474 | C33: PPMG | D33: Sprint 16 2026 | E33: Validated | F33: indeterminate | G33: Bug | H33: Medium | I33: Yassine BOUARI | J33: [OTD 207474] Trouver la cause du changement du thème des environnements | K33: 46030.529 | L33: 46178.571 | M33: 150.81 | N33: 2.77 | O33: FALSE | P33: missing | Q33: 3 | R33: 1 | S33: 0 | T33: https://data-servier.atlassian.net/browse/PPMG-1474
A34: 342847 | B34: PPMG-1476 | C34: PPMG | E34: Backlog | F34: new | G34: Story | H34: Low | I34: Yosra MANAI | J34: [GLOBAL] Champs attendus en Read-Only | K34: 46031.37 | L34: 46031.37 | M34: 149.97 | N34: 149.97 | O34: FALSE | P34: missing | Q34: 0 | R34: 0 | S34: 0 | T34: https://data-servier.atlassian.net/browse/PPMG-1476
A35: 343177 | B35: PPMG-1477 | C35: PPMG | D35: Sprint 15 2026 | E35: Candidate | F35: new | G35: Change | H35: High | I35: RACHEL CLOIX | J35: VYP – Analyse des droits d’écriture pour les Gatekeepers des programmes SPOT | K35: 46031.655 | L35: 46113.35 | M35: 149.68 | N35: 67.99 | O35: TRUE | P35: customfield: Acceptance Criteria | Q35: 2 | R35: 0 | S35: 0 | T35: https://data-servier.atlassian.net/browse/PPMG-1477
A36: 345010 | B36: PPMG-1479 | C36: PPMG | E36: Backlog | F36: new | G36: Feature | H36: Medium | I36: Non assigné | J36: MIGRATION | K36: 46036.531 | L36: 46037.597 | M36: 144.81 | N36: 143.74 | O36: FALSE | P36: missing | Q36: 0 | R36: 0 | S36: 0 | T36: https://data-servier.atlassian.net/browse/PPMG-1479
A37: 345593 | B37: PPMG-1482 | C37: PPMG | D37: Sprint 16 2026 | E37: En cours | F37: indeterminate | G37: Bug | H37: Highest | I37: Yassine BOUARI | J37: [OTD 208287] Les Key Risks ne s’affichent pas dans l’export PDF de l’Initiative Dashboard (OK dans l’export PPT) | K37: 46037.462 | L37: 46178.541 | M37: 143.88 | N37: 2.8 | O37: TRUE | P37: customfield: Acceptance Criteria | Q37: 6 | R37: 4 | S37: 0 | T37: https://data-servier.atlassian.net/browse/PPMG-1482
A38: 347980 | B38: PPMG-1483 | C38: PPMG | D38: Sprint 17 2026 | E38: Backlog | F38: new | G38: Tâche | H38: Medium | I38: Non assigné | J38: Interfaçage MDM | K38: 46043.539 | L38: 46113.356 | M38: 137.8 | N38: 67.98 | O38: FALSE | P38: missing | Q38: 1 | R38: 1 | S38: 0 | T38: https://data-servier.atlassian.net/browse/PPMG-1483
A39: 351111 | B39: PPMG-1486 | C39: PPMG | E39: Ready for Development | F39: new | G39: Story | H39: Low | I39: Yassine BOUARI | J39: [SPM] [Cost&Load] Refonte et harmonisation des notions ETC / EAC dans le module Strategic Portfolios | K39: 46050.361 | L39: 46092.583 | M39: 130.98 | N39: 88.76 | O39: TRUE | P39: customfield: Acceptance Criteria | Q39: 0 | R39: 1 | S39: 1 | T39: https://data-servier.atlassian.net/browse/PPMG-1486
A40: 360128 | B40: PPMG-1491 | C40: PPMG | D40: Sprint 14 2026; Sprint 15 2026 | E40: Backlog | F40: new | G40: Story | H40: Medium | I40: RACHEL CLOIX | J40: [R&D] - INTERFACE DP - VYP - Remontée du réel | K40: 46070.439 | L40: 46126.623 | M40: 110.9 | N40: 54.71 | O40: FALSE | P40: missing | Q40: 3 | R40: 0 | S40: 0 | T40: https://data-servier.atlassian.net/browse/PPMG-1491
A41: 360846 | B41: PPMG-1495 | C41: PPMG | E41: Ouvert | F41: new | G41: Bug | H41: Medium | I41: Patrick PONCET | J41: [OTD209092] [COST & LOAD] Répartition mensuelle différente entre des Forecast & Actuals identiques sur une saisie à l'année | K41: 46071.482 | L41: 46140.416 | M41: 109.86 | N41: 40.92 | O41: FALSE | P41: missing | Q41: 0 | R41: 0 | S41: 0 | T41: https://data-servier.atlassian.net/browse/PPMG-1495
A42: 362615 | B42: PPMG-1498 | C42: PPMG | D42: Sprint 17 2026 | E42: Backlog | F42: new | G42: Story | H42: Medium | I42: RACHEL CLOIX | J42: [A compléter] Interface VYP - MDM Group Project | K42: 46076.562 | L42: 46106.383 | M42: 104.78 | N42: 74.96 | O42: FALSE | P42: missing | Q42: 0 | R42: 0 | S42: 0 | T42: https://data-servier.atlassian.net/browse/PPMG-1498
A43: 362723 | B43: PPMG-1500 | C43: PPMG | E43: Ouvert | F43: new | G43: Bug | H43: Medium | I43: Romain CIESLIK | J43: [OTD XXX] [INC0853680] - La recherche globale via 'filter' ne retourne aucun résultat après sélection d’un portefeuille dans ALL PROJECTS | K43: 46076.647 | L43: 46133.413 | M43: 104.69 | N43: 47.93 | O43: FALSE | P43: missing | Q43: 0 | R43: 0 | S43: 0 | T43: https://data-servier.atlassian.net/browse/PPMG-1500
A44: 363136 | B44: PPMG-1501 | C44: PPMG | D44: Sprint 14 2026; Sprint 15 2026 | E44: Backlog | F44: new | G44: Story | H44: Highest | I44: RACHEL CLOIX | J44: Double comptabilisation du forecast sur la page Cost & Load ( au niveau Projet + WorkPackages) | K44: 46077.452 | L44: 46126.623 | M44: 103.89 | N44: 54.71 | O44: FALSE | P44: missing | Q44: 0 | R44: 3 | S44: 1 | T44: https://data-servier.atlassian.net/browse/PPMG-1501
A45: 363485 | B45: PPMG-1502 | C45: PPMG | D45: Sprint 17 2026 | E45: Ready for Development | F45: new | G45: Story | H45: Highest | I45: Patrick PONCET | J45: [Ergonomie] Page Properties - Initiative Summary | K45: 46077.668 | L45: 46146.62 | M45: 103.67 | N45: 34.72 | O45: TRUE | P45: customfield: Acceptance Criteria | Q45: 0 | R45: 2 | S45: 0 | T45: https://data-servier.atlassian.net/browse/PPMG-1502
A46: 363513 | B46: PPMG-1503 | C46: PPMG | D46: Sprint 17 2026 | E46: Backlog | F46: new | G46: Story | H46: Medium | I46: Yosra MANAI | J46: [Ergonomie] Dashboard > ID Card | K46: 46077.716 | L46: 46141.503 | M46: 103.62 | N46: 39.84 | O46: TRUE | P46: description: expected/acceptance markers | Q46: 0 | R46: 0 | S46: 0 | T46: https://data-servier.atlassian.net/browse/PPMG-1503
A47: 363523 | B47: PPMG-1504 | C47: PPMG | D47: Sprint 17 2026 | E47: Backlog | F47: new | G47: Story | H47: Medium | I47: Yosra MANAI | J47: [Ergonomie] Dashboard > Initiative Dashboard | K47: 46077.719 | L47: 46141.503 | M47: 103.62 | N47: 39.84 | O47: TRUE | P47: description: expected/acceptance markers | Q47: 0 | R47: 0 | S47: 0 | T47: https://data-servier.atlassian.net/browse/PPMG-1504
A48: 363885 | B48: PPMG-1505 | C48: PPMG | D48: Sprint 17 2026 | E48: Backlog | F48: new | G48: Story | H48: Medium | I48: RACHEL CLOIX | J48: [MDM Référentiel Projet Groupe] Impacts VYP et Interface VYP-MDM ref Projet Groupe | K48: 46078.46 | L48: 46106.383 | M48: 102.88 | N48: 74.96 | O48: FALSE | P48: missing | Q48: 1 | R48: 0 | S48: 0 | T48: https://data-servier.atlassian.net/browse/PPMG-1505
A49: 366711 | B49: PPMG-1507 | C49: PPMG | E49: Ouvert | F49: new | G49: Bug | H49: Low | I49: Yassine BOUARI | J49: "Forecast up to date" - dysfonctionnement | K49: 46083.711 | L49: 46174.638 | M49: 97.63 | N49: 6.7 | O49: FALSE | P49: missing | Q49: 1 | R49: 4 | S49: 0 | T49: https://data-servier.atlassian.net/browse/PPMG-1507
A50: 367082 | B50: PPMG-1508 | C50: PPMG | D50: Sprint 15 2026 | E50: Analyse | F50: indeterminate | G50: Story | H50: Highest | I50: Non assigné | J50: [AMOA] [TEST] Création de profils utilisateurs IO et PFM en PROD pour testing | K50: 46084.447 | L50: 46108.637 | M50: 96.89 | N50: 72.7 | O50: FALSE | P50: missing | Q50: 0 | R50: 0 | S50: 0 | T50: https://data-servier.atlassian.net/browse/PPMG-1508
A51: 371407 | B51: PPMG-1512 | C51: PPMG | E51: Backlog | F51: new | G51: Story | H51: Medium | I51: Typhaine MICHEL | J51: [COST&LOAD] Saisie des coûts sur un workpackage | K51: 46091.197 | L51: 46106.382 | M51: 90.14 | N51: 74.96 | O51: FALSE | P51: missing | Q51: 1 | R51: 0 | S51: 0 | T51: https://data-servier.atlassian.net/browse/PPMG-1512
A52: 372247 | B52: PPMG-1516 | C52: PPMG | D52: Sprint 17 2026 | E52: Ready for Development | F52: new | G52: Story | H52: Highest | I52: Yassine BOUARI | J52: [Ergonomie] Page Gantt - Mode Fold | K52: 46092.587 | L52: 46141.501 | M52: 88.75 | N52: 39.84 | O52: TRUE | P52: customfield: Acceptance Criteria | Q52: 3 | R52: 1 | S52: 1 | T52: https://data-servier.atlassian.net/browse/PPMG-1516
A53: 372342 | B53: PPMG-1517 | C53: PPMG | D53: Sprint 15 2026 | E53: Backlog | F53: new | G53: Story | H53: Medium | I53: Typhaine MICHEL | J53: [Risques] Risk amelioration/Evolutions - 3 (Export/Import) | K53: 46092.662 | L53: 46155.424 | M53: 88.68 | N53: 25.91 | O53: TRUE | P53: customfield: Acceptance Criteria | Q53: 8 | R53: 1 | S53: 0 | T53: https://data-servier.atlassian.net/browse/PPMG-1517
A54: 375988 | B54: PPMG-1521 | C54: PPMG | E54: Ouvert | F54: new | G54: Bug | H54: Medium | I54: Romain CIESLIK | J54: Ligne dans Planned hours avec un cost account vide | K54: 46100.383 | L54: 46133.411 | M54: 80.95 | N54: 47.93 | O54: TRUE | P54: customfield: Acceptance Criteria | Q54: 0 | R54: 1 | S54: 0 | T54: https://data-servier.atlassian.net/browse/PPMG-1521
A55: 380552 | B55: PPMG-1525 | C55: PPMG | D55: Sprint 15 2026 | E55: Go Prod | F55: indeterminate | G55: Story | H55: Highest | I55: Yassine BOUARI | J55: [AMOA] Mise à jour OBS -> Department Lead & Department Involved | K55: 46108.619 | L55: 46178.417 | M55: 72.72 | N55: 2.92 | O55: FALSE | P55: missing | Q55: 22 | R55: 19 | S55: 0 | T55: https://data-servier.atlassian.net/browse/PPMG-1525
A56: 382354 | B56: PPMG-1527 | C56: PPMG | D56: Sprint 15 2026 | E56: Ouvert | F56: new | G56: Bug | H56: High | I56: Romain CIESLIK | J56: [INC0874083] - Changement de catégorie non pris en compte Value Business Case | K56: 46113.445 | L56: 46140.416 | M56: 67.89 | N56: 40.92 | O56: FALSE | P56: missing | Q56: 0 | R56: 1 | S56: 0 | T56: https://data-servier.atlassian.net/browse/PPMG-1527
A57: 382401 | B57: PPMG-1528 | C57: PPMG | D57: Sprint 15 2026 | E57: Backlog | F57: new | G57: Story | H57: Highest | I57: RACHEL CLOIX | J57: [R&D] Remontée du réel - Evolution du dev suite à reprise du besoin | K57: 46113.515 | L57: 46113.516 | M57: 67.82 | N57: 67.82 | O57: FALSE | P57: missing | Q57: 0 | R57: 0 | S57: 0 | T57: https://data-servier.atlassian.net/browse/PPMG-1528
A58: 384372 | B58: PPMG-1530 | C58: PPMG | E58: Backlog | F58: new | G58: Story | H58: Medium | I58: Non assigné | J58: [STAGE & GATE] Empêcher la validation d'une gate si la date de la gate est dans le futur | K58: 46119.427 | L58: 46119.427 | M58: 61.91 | N58: 61.91 | O58: FALSE | P58: missing | Q58: 0 | R58: 0 | S58: 0 | T58: https://data-servier.atlassian.net/browse/PPMG-1530
A59: 385510 | B59: PPMG-1533 | C59: PPMG | D59: Sprint 15 2026 | E59: Ouvert | F59: new | G59: Bug | H59: Highest | I59: Romain CIESLIK | J59: Error message displayed when portfolio applied_Test Environment | K59: 46121.435 | L59: 46149.615 | M59: 59.9 | N59: 31.72 | O59: FALSE | P59: missing | Q59: 1 | R59: 2 | S59: 0 | T59: https://data-servier.atlassian.net/browse/PPMG-1533
A60: 387351 | B60: PPMG-1534 | C60: PPMG | D60: Sprint 17 2026 | E60: Ready for Development | F60: new | G60: Story | H60: Highest | I60: Yassine BOUARI | J60: [Ergonomie] Module Home - Categories/Workboxes​ | K60: 46125.317 | L60: 46141.502 | M60: 56.02 | N60: 39.84 | O60: TRUE | P60: customfield: Acceptance Criteria | Q60: 0 | R60: 1 | S60: 0 | T60: https://data-servier.atlassian.net/browse/PPMG-1534
A61: 387457 | B61: PPMG-1535 | C61: PPMG | D61: Sprint 17 2026 | E61: Ready for Development | F61: new | G61: Story | H61: Highest | I61: Yassine BOUARI | J61: [Ergonomie] Barre de menu principale | K61: 46125.355 | L61: 46141.502 | M61: 55.98 | N61: 39.84 | O61: TRUE | P61: customfield: Acceptance Criteria | Q61: 3 | R61: 1 | S61: 1 | T61: https://data-servier.atlassian.net/browse/PPMG-1535
A62: 387523 | B62: PPMG-1537 | C62: PPMG | D62: Sprint 17 2026 | E62: Ready for Development | F62: new | G62: Story | H62: Highest | I62: Yassine BOUARI | J62: [Ergonomie] Module Projects - Configuration des pages par profil | K62: 46125.386 | L62: 46141.502 | M62: 55.95 | N62: 39.84 | O62: TRUE | P62: customfield: Acceptance Criteria | Q62: 2 | R62: 0 | S62: 0 | T62: https://data-servier.atlassian.net/browse/PPMG-1537
A63: 388732 | B63: PPMG-1539 | C63: PPMG | D63: Sprint 15 2026 | E63: En cours | F63: indeterminate | G63: Bug | H63: Highest | I63: Romain CIESLIK | J63: [INC0879976] Analyse des points d’appel du User Attribute SER_UA_PRJ_TEMPLATE_FILTER | K63: 46126.631 | L63: 46155.317 | M63: 54.71 | N63: 26.02 | O63: FALSE | P63: missing | Q63: 1 | R63: 0 | S63: 0 | T63: https://data-servier.atlassian.net/browse/PPMG-1539
A64: 389042 | B64: PPMG-1540 | C64: PPMG | D64: Sprint 16 2026 | E64: En cours | F64: indeterminate | G64: Tâche | H64: Medium | I64: Yassine BOUARI | J64: [MOE] UPGRADE v7.1.6 - Créer la liste des fonctionnalités | K64: 46127.371 | L64: 46175.307 | M64: 53.97 | N64: 6.03 | O64: TRUE | P64: customfield: Acceptance Criteria | Q64: 1 | R64: 1 | S64: 0 | T64: https://data-servier.atlassian.net/browse/PPMG-1540
A65: 390477 | B65: PPMG-1541 | C65: PPMG | E65: Backlog | F65: new | G65: Story | H65: Medium | I65: Non assigné | J65: Comment Gate Log | K65: 46128.615 | L65: 46128.615 | M65: 52.72 | N65: 52.72 | O65: FALSE | P65: missing | Q65: 0 | R65: 0 | S65: 0 | T65: https://data-servier.atlassian.net/browse/PPMG-1541
A66: 391357 | B66: PPMG-1542 | C66: PPMG | E66: Backlog | F66: new | G66: Story | H66: Medium | I66: Non assigné | J66: Write access sur les projets enfants | K66: 46129.333 | L66: 46129.333 | M66: 52.01 | N66: 52.01 | O66: TRUE | P66: description: expected/acceptance markers | Q66: 0 | R66: 0 | S66: 0 | T66: https://data-servier.atlassian.net/browse/PPMG-1542
A67: 391358 | B67: PPMG-1543 | C67: PPMG | E67: Backlog | F67: new | G67: Story | H67: Medium | I67: Non assigné | J67: Column to add un the Cost data reporting | K67: 46129.333 | L67: 46129.333 | M67: 52.01 | N67: 52.01 | O67: FALSE | P67: missing | Q67: 0 | R67: 0 | S67: 0 | T67: https://data-servier.atlassian.net/browse/PPMG-1543
A68: 391359 | B68: PPMG-1544 | C68: PPMG | E68: Backlog | F68: new | G68: Story | H68: Medium | I68: Non assigné | J68: Cost data reporting evolution | K68: 46129.334 | L68: 46129.334 | M68: 52 | N68: 52 | O68: FALSE | P68: missing | Q68: 0 | R68: 0 | S68: 0 | T68: https://data-servier.atlassian.net/browse/PPMG-1544
A69: 391360 | B69: PPMG-1545 | C69: PPMG | E69: Backlog | F69: new | G69: Story | H69: Medium | I69: Non assigné | J69: Budget Allocation - Filtre External/full costs | K69: 46129.334 | L69: 46129.334 | M69: 52 | N69: 52 | O69: FALSE | P69: missing | Q69: 0 | R69: 0 | S69: 0 | T69: https://data-servier.atlassian.net/browse/PPMG-1545
A70: 391361 | B70: PPMG-1546 | C70: PPMG | E70: Backlog | F70: new | G70: Story | H70: Medium | I70: Non assigné | J70: Rapport Portfolio Timeline - ajout de filtres | K70: 46129.334 | L70: 46129.334 | M70: 52 | N70: 52 | O70: FALSE | P70: missing | Q70: 0 | R70: 0 | S70: 0 | T70: https://data-servier.atlassian.net/browse/PPMG-1546
A71: 392012 | B71: PPMG-1548 | C71: PPMG | E71: Backlog | F71: new | G71: Story | H71: Low | I71: Non assigné | J71: [AMOA] Suppression des utilisateurs BIOGARAN | K71: 46129.767 | L71: 46129.767 | M71: 51.57 | N71: 51.57 | O71: FALSE | P71: missing | Q71: 0 | R71: 0 | S71: 0 | T71: https://data-servier.atlassian.net/browse/PPMG-1548
A72: 392738 | B72: PPMG-1549 | C72: PPMG | D72: Sprint 17 2026 | E72: In Refinement | F72: indeterminate | G72: Story | H72: High | I72: Patrick PONCET | J72: Gantt - Règles de gestion et contrôles d'intégrité – Librairie "DDIS-MVP" | K72: 46133.337 | L72: 46178.662 | M72: 48 | N72: 2.68 | O72: TRUE | P72: customfield: Acceptance Criteria | Q72: 4 | R72: 0 | S72: 1 | T72: https://data-servier.atlassian.net/browse/PPMG-1549
A73: 392839 | B73: PPMG-1550 | C73: PPMG | D73: Sprint 17 2026 | E73: Candidate | F73: new | G73: Story | H73: High | I73: RACHEL CLOIX | J73: Intégration Data Platform – Librairie "DDIS-MVP" | K73: 46133.396 | L73: 46148.374 | M73: 47.94 | N73: 32.96 | O73: TRUE | P73: customfield: Acceptance Criteria | Q73: 2 | R73: 2 | S73: 0 | T73: https://data-servier.atlassian.net/browse/PPMG-1550
A74: 393117 | B74: PPMG-1551 | C74: PPMG | D74: Sprint 17 2026 | E74: Ready for Development | F74: new | G74: Story | H74: Highest | I74: Patrick PONCET | J74: [Ergonomie] Module Portfolio Reporting - Reports | K74: 46133.634 | L74: 46141.502 | M74: 47.7 | N74: 39.84 | O74: TRUE | P74: customfield: Acceptance Criteria | Q74: 3 | R74: 1 | S74: 0 | T74: https://data-servier.atlassian.net/browse/PPMG-1551
A75: 393585 | B75: PPMG-1552 | C75: PPMG | E75: Backlog | F75: new | G75: Story | H75: Medium | I75: Yosra MANAI | J75: [PILOT] Règles de gestion et contrôles pour les champs d'interface PILOT | K75: 46134.501 | L75: 46134.52 | M75: 46.84 | N75: 46.82 | O75: TRUE | P75: description: expected/acceptance markers | Q75: 0 | R75: 0 | S75: 0 | T75: https://data-servier.atlassian.net/browse/PPMG-1552
A76: 393730 | B76: PPMG-1553 | C76: PPMG | D76: Sprint 17 2026 | E76: Ready for Development | F76: new | G76: Story | H76: Highest | I76: Patrick PONCET | J76: [Ergonomie] Page Properties - Initiative Health Status | K76: 46134.622 | L76: 46142.346 | M76: 46.72 | N76: 38.99 | O76: TRUE | P76: customfield: Acceptance Criteria | Q76: 0 | R76: 1 | S76: 0 | T76: https://data-servier.atlassian.net/browse/PPMG-1553
A77: 394245 | B77: PPMG-1556 | C77: PPMG | E77: Ouvert | F77: new | G77: Xray Test | H77: Medium | I77: Non assigné | J77: Test 1 | K77: 46135.542 | L77: 46135.542 | M77: 45.8 | N77: 45.8 | O77: FALSE | P77: missing | Q77: 0 | R77: 0 | S77: 0 | T77: https://data-servier.atlassian.net/browse/PPMG-1556
A78: 394246 | B78: PPMG-1557 | C78: PPMG | E78: Backlog | F78: new | G78: Test Execution | H78: Medium | I78: Herve ONNO | J78: Exécution Ad-hoc de PPMG-1556 | K78: 46135.545 | L78: 46135.545 | M78: 45.79 | N78: 45.79 | O78: FALSE | P78: missing | Q78: 0 | R78: 0 | S78: 0 | T78: https://data-servier.atlassian.net/browse/PPMG-1557
A79: 395612 | B79: PPMG-1558 | C79: PPMG | D79: Sprint 17 2026 | E79: Selected | F79: indeterminate | G79: Feature | H79: Medium | I79: Non assigné | J79: ERGONOMIE | K79: 46139.668 | L79: 46141.501 | M79: 41.67 | N79: 39.84 | O79: FALSE | P79: missing | Q79: 0 | R79: 0 | S79: 0 | T79: https://data-servier.atlassian.net/browse/PPMG-1558
A80: 395624 | B80: PPMG-1559 | C80: PPMG | D80: Sprint 17 2026 | E80: Ready for Development | F80: new | G80: Story | H80: Highest | I80: Patrick PONCET | J80: [Ergonomie] New Project Popup | K80: 46139.688 | L80: 46142.345 | M80: 41.65 | N80: 38.99 | O80: TRUE | P80: customfield: Acceptance Criteria | Q80: 7 | R80: 1 | S80: 0 | T80: https://data-servier.atlassian.net/browse/PPMG-1559
A81: 395628 | B81: PPMG-1560 | C81: PPMG | D81: Sprint 17 2026 | E81: Ready for Development | F81: new | G81: Story | H81: Highest | I81: Patrick PONCET | J81: [Ergonomie] Liste des onglets - Task Popup | K81: 46139.707 | L81: 46141.502 | M81: 41.63 | N81: 39.84 | O81: TRUE | P81: customfield: Acceptance Criteria | Q81: 0 | R81: 1 | S81: 0 | T81: https://data-servier.atlassian.net/browse/PPMG-1560
A82: 395641 | B82: PPMG-1561 | C82: PPMG | D82: Sprint 17 2026 | E82: Ready for Development | F82: new | G82: Story | H82: Highest | I82: Patrick PONCET | J82: [Ergonomie] New Task/ WBS Element Popup | K82: 46139.739 | L82: 46142.343 | M82: 41.6 | N82: 39 | O82: TRUE | P82: customfield: Acceptance Criteria | Q82: 2 | R82: 1 | S82: 0 | T82: https://data-servier.atlassian.net/browse/PPMG-1561
A83: 395646 | B83: PPMG-1562 | C83: PPMG | D83: Sprint 17 2026 | E83: Ready for Development | F83: new | G83: Story | H83: Highest | I83: Patrick PONCET | J83: [Ergonomie] New Forecast Popup | K83: 46139.755 | L83: 46142.344 | M83: 41.58 | N83: 38.99 | O83: TRUE | P83: customfield: Acceptance Criteria | Q83: 3 | R83: 1 | S83: 0 | T83: https://data-servier.atlassian.net/browse/PPMG-1562
A84: 395656 | B84: PPMG-1563 | C84: PPMG | D84: Sprint 17 2026 | E84: Ready for Development | F84: new | G84: Story | H84: Highest | I84: Patrick PONCET | J84: [Ergonomie] Page Properties - ID Card | K84: 46139.819 | L84: 46141.503 | M84: 41.52 | N84: 39.84 | O84: TRUE | P84: customfield: Acceptance Criteria | Q84: 2 | R84: 0 | S84: 0 | T84: https://data-servier.atlassian.net/browse/PPMG-1563
A85: 395847 | B85: PPMG-1565 | C85: PPMG | D85: Sprint 16 2026 | E85: En cours | F85: indeterminate | G85: Tâche | H85: Medium | I85: Yassine BOUARI | J85: [MOE] - Comparaison des fonctionnalités 7.0.6 VS 7.1.6 | K85: 46140.359 | L85: 46175.309 | M85: 40.98 | N85: 6.03 | O85: TRUE | P85: customfield: Acceptance Criteria | Q85: 1 | R85: 1 | S85: 0 | T85: https://data-servier.atlassian.net/browse/PPMG-1565
A86: 395879 | B86: PPMG-1566 | C86: PPMG | D86: Sprint 16 2026 | E86: En cours | F86: indeterminate | G86: Tâche | H86: Medium | I86: Yassine BOUARI | J86: [MOE] - Lister les répertoires des diverses interfaces pour partage à PLW | K86: 46140.385 | L86: 46154.35 | M86: 40.95 | N86: 26.99 | O86: FALSE | P86: missing | Q86: 0 | R86: 0 | S86: 0 | T86: https://data-servier.atlassian.net/browse/PPMG-1566
A87: 395880 | B87: PPMG-1567 | C87: PPMG | D87: Sprint 16 2026 | E87: En cours | F87: indeterminate | G87: Tâche | H87: Medium | I87: Yassine BOUARI | J87: [MOE] - Lister tables Admin fonctionnel pour faciliter l'administration des données avec version 7.1.6 | K87: 46140.386 | L87: 46155.452 | M87: 40.95 | N87: 25.89 | O87: FALSE | P87: missing | Q87: 1 | R87: 1 | S87: 0 | T87: https://data-servier.atlassian.net/browse/PPMG-1567
A88: 396904 | B88: PPMG-1568 | C88: PPMG | E88: Backlog | F88: new | G88: Story | H88: High | I88: Yassine BOUARI | J88: [INTERFACE VYP-DP] - Ajout du champ "Level" dans l'export des activités | K88: 46142.342 | L88: 46142.342 | M88: 39 | N88: 39 | O88: TRUE | P88: customfield: Acceptance Criteria | Q88: 0 | R88: 0 | S88: 0 | T88: https://data-servier.atlassian.net/browse/PPMG-1568
A89: 399924 | B89: PPMG-1570 | C89: PPMG | D89: Sprint 15 2026 | E89: Ouvert | F89: new | G89: Bug | H89: Medium | I89: RACHEL CLOIX | J89: Restituer l’intégralité des données de référence dans Cost & Load, y compris lorsque des coûts courants ont été supprimés | K89: 46153.424 | L89: 46177.61 | M89: 27.91 | N89: 3.73 | O89: TRUE | P89: customfield: Acceptance Criteria | Q89: 1 | R89: 2 | S89: 0 | T89: https://data-servier.atlassian.net/browse/PPMG-1570
A90: 400599 | B90: PPMG-1571 | C90: PPMG | E90: Ouvert | F90: new | G90: Xray Test | H90: Medium | I90: Non assigné | J90: Affichage du menu Planisware Enterprise | K90: 46154.581 | L90: 46154.581 | M90: 26.76 | N90: 26.76 | O90: FALSE | P90: missing | Q90: 0 | R90: 0 | S90: 0 | T90: https://data-servier.atlassian.net/browse/PPMG-1571
A91: 400600 | B91: PPMG-1572 | C91: PPMG | E91: Ouvert | F91: new | G91: Xray Test | H91: Medium | I91: Non assigné | J91: Présence des sous-menus standards | K91: 46154.581 | L91: 46154.581 | M91: 26.76 | N91: 26.76 | O91: FALSE | P91: missing | Q91: 0 | R91: 0 | S91: 0 | T91: https://data-servier.atlassian.net/browse/PPMG-1572
A92: 400607 | B92: PPMG-1574 | C92: PPMG | E92: Ouvert | F92: new | G92: Xray Test | H92: Medium | I92: Non assigné | J92: Affichage du menu Planisware Enterprise | K92: 46154.601 | L92: 46154.601 | M92: 26.74 | N92: 26.74 | O92: FALSE | P92: missing | Q92: 0 | R92: 0 | S92: 0 | T92: https://data-servier.atlassian.net/browse/PPMG-1574
A93: 400608 | B93: PPMG-1575 | C93: PPMG | E93: Ouvert | F93: new | G93: Xray Test | H93: Medium | I93: Non assigné | J93: Présence des sous-menus standards | K93: 46154.601 | L93: 46154.601 | M93: 26.74 | N93: 26.74 | O93: FALSE | P93: missing | Q93: 0 | R93: 0 | S93: 0 | T93: https://data-servier.atlassian.net/browse/PPMG-1575
A94: 403089 | B94: PPMG-1577 | C94: PPMG | E94: Backlog | F94: new | G94: Test Execution | H94: Medium | I94: Pierre KAYA | J94: Exécution Ad-hoc de PPMG-1574 | K94: 46161.386 | L94: 46161.386 | M94: 19.95 | N94: 19.95 | O94: FALSE | P94: missing | Q94: 0 | R94: 0 | S94: 0 | T94: https://data-servier.atlassian.net/browse/PPMG-1577
A95: 403230 | B95: PPMG-1578 | C95: PPMG | E95: Ouvert | F95: new | G95: Xray Test | H95: Medium | I95: Non assigné | J95: Affichage du menu Planisware Enterprise | K95: 46161.394 | L95: 46161.394 | M95: 19.94 | N95: 19.94 | O95: FALSE | P95: missing | Q95: 0 | R95: 0 | S95: 0 | T95: https://data-servier.atlassian.net/browse/PPMG-1578
A96: 403232 | B96: PPMG-1579 | C96: PPMG | E96: Ouvert | F96: new | G96: Xray Test | H96: Medium | I96: Non assigné | J96: Présence des sous-menus standards | K96: 46161.394 | L96: 46161.394 | M96: 19.94 | N96: 19.94 | O96: FALSE | P96: missing | Q96: 0 | R96: 0 | S96: 0 | T96: https://data-servier.atlassian.net/browse/PPMG-1579
A97: 403487 | B97: PPMG-1580 | C97: PPMG | E97: Ouvert | F97: new | G97: Xray Test | H97: Medium | I97: Non assigné | J97: TESTING IMPORT | K97: 46161.398 | L97: 46161.398 | M97: 19.94 | N97: 19.94 | O97: FALSE | P97: missing | Q97: 0 | R97: 0 | S97: 0 | T97: https://data-servier.atlassian.net/browse/PPMG-1580
A98: 403489 | B98: PPMG-1581 | C98: PPMG | E98: Ouvert | F98: new | G98: Xray Test | H98: Medium | I98: Non assigné | J98: Présence des sous-menus standards | K98: 46161.398 | L98: 46161.398 | M98: 19.94 | N98: 19.94 | O98: FALSE | P98: missing | Q98: 0 | R98: 0 | S98: 0 | T98: https://data-servier.atlassian.net/browse/PPMG-1581
A99: 403607 | B99: PPMG-1582 | C99: PPMG | E99: Ouvert | F99: new | G99: Xray Test | H99: Medium | I99: Non assigné | J99: TESTING IMPORT | K99: 46161.4 | L99: 46161.4 | M99: 19.94 | N99: 19.94 | O99: FALSE | P99: missing | Q99: 0 | R99: 0 | S99: 0 | T99: https://data-servier.atlassian.net/browse/PPMG-1582
A100: 403609 | B100: PPMG-1583 | C100: PPMG | E100: Ouvert | F100: new | G100: Xray Test | H100: Medium | I100: Non assigné | J100: TESTING IMPORT | K100: 46161.4 | L100: 46161.4 | M100: 19.94 | N100: 19.94 | O100: FALSE | P100: missing | Q100: 0 | R100: 0 | S100: 0 | T100: https://data-servier.atlassian.net/browse/PPMG-1583
...

Sheet Limites
A1: Sujet | B1: Message
A2: Nature de la date | B2: Les dates de modification sont des fenêtres de détection entre deux exports RSS. Le RSS ne donne pas l'heure exacte ni l'auteur exact de chaque changement de champ.
A3: Identifiant ticket | B3: La comparaison utilise l'id technique de <key id=...>. Si absent, le script utilise la key Jira et l'indique dans les warnings.
A4: Tickets disparus | B4: Un ticket disparu signifie qu'il est absent de l'export suivant. Cela peut venir d'une clôture, d'un changement de filtre Jira, d'un droit d'accès ou d'une suppression.
A5: Filtres Jira | B5: Pour des comparaisons fiables, tous les fichiers du répertoire doivent provenir du même filtre Jira ou d'un périmètre fonctionnel comparable.
